src/io_ctrl.sv
module io_ctrl (
    input  logic clk, rst, ena,
    input  logic ui_in0, ui_in1,
    output logic load_pulse,
    output logic output_pulse,
    output logic [1:0] addr
);
    logic [1:0] counter;
    logic prev_in0, prev_in1;
    
    always_ff @(posedge clk or posedge rst) begin
        if (rst) begin
            counter <= '0;
            prev_in0 <= '0;
            prev_in1 <= '0;
        end else if (ena) begin
            prev_in0 <= ui_in0;
            prev_in1 <= ui_in1;
            
            if (ui_in0 && !prev_in0) begin
                counter <= counter + 1;
            end
        end
    end
    
    assign load_pulse = ui_in0 && !prev_in0;
    assign output_pulse = ui_in1 && !prev_in1;
    assign addr = counter;
endmodule

test/io_ctrl/io_ctrl_tb.sv
`default_nettype none
`timescale 1ns / 1ps

module io_ctrl_tb (
    // Control and Input signals
    input  logic clk,
    input  logic rst,
    input  logic ena,
    input  logic ui_in0,
    input  logic ui_in1,

    // Output signals
    output logic load_pulse,
    output logic output_pulse,
    output logic [1:0] addr
);

    // Dump signals for waveform viewing
    string vcd_name;
    initial begin
`ifdef VCD_PATH
        vcd_name = `VCD_PATH;
`else
        vcd_name = {"io_ctrl_tb_", `TIMESTAMP, ".vcd"};
`endif
        $dumpfile(vcd_name);
        $dumpvars(0, io_ctrl_tb);
        #1;
    end

    // Instantiate the DUT
    io_ctrl dut (
        .clk(clk),
        .rst(rst),
        .ena(ena),
        .ui_in0(ui_in0),
        .ui_in1(ui_in1),
        .load_pulse(load_pulse),
        .output_pulse(output_pulse),
        .addr(addr)
    );

endmodule

test/io_ctrl/wave/io_ctrl_tb_20250703_00:18:54.vcd
$date
	Thu Jul  3 00:18:59 2025
$end
$version
	Icarus Verilog
$end
$timescale
	1ps
$end
$scope module io_ctrl_tb $end
$var wire 1 ! clk $end
$var wire 1 " ena $end
$var wire 1 # rst $end
$var wire 1 $ ui_in0 $end
$var wire 1 % ui_in1 $end
$var wire 1 & output_pulse $end
$var wire 1 ' load_pulse $end
$var wire 2 ( addr [1:0] $end
$scope module dut $end
$var wire 2 ) addr [1:0] $end
$var wire 1 ! clk $end
$var wire 1 " ena $end
$var wire 1 ' load_pulse $end
$var wire 1 & output_pulse $end
$var wire 1 # rst $end
$var wire 1 $ ui_in0 $end
$var wire 1 % ui_in1 $end
$var reg 2 * counter [1:0] $end
$var reg 1 + prev_in0 $end
$var reg 1 , prev_in1 $end
$upscope $end
$upscope $end
$enddefinitions $end
#0
$dumpvars
z,
1+
bx *
bx )
bx (
0'
x&
z%
1$
z#
1"
1!
$end
#5000
0!
#10000
0,
0+
b0 (
b0 )
b0 *
1#
0$
1!
#15001
0&
0%
0"
#20001
0!
0#
#25001
1'
1$
1"
1!
#30001
0!
#35001
0'
b1 (
b1 )
b1 *
1+
1!
#35002
0+
b0 (
b0 )
b0 *
0$
0"
1#
#40002
0!
0#
#45002
1&
1%
1"
1!
#50002
0!
#55002
0&
1,
1!
#60002
0!
#65002
1!
#65003
0,
0%
0"
1#
#70003
0!
0#
#75003
1'
1$
1"
1!
#80003
0!
#85003
0$
0'
b1 (
b1 )
b1 *
1+
1!
#90003
0!
#95003
1&
1'
1%
1$
0"
0+
1!
#100003
0!
#105003
1!
#105004
b0 (
b0 )
b0 *
0&
0'
0%
0$
1#
#110004
0!
0#
#115004
1&
1'
1%
1$
1"
1!
#120004
0!
#125004
0&
0'
b1 (
b1 )
b1 *
1,
1+
1!
