src/memory_ctrl.sv
module memory_ctrl #(
    parameter WIDTH = 8
)(
    input  logic clk, rst, ena,
    input  logic load_pulse,
    input  logic [1:0] addr,
    input  logic [7:0] data_in,
    output logic signed [WIDTH-1:0] real0_out, imag0_out,
    output logic signed [WIDTH-1:0] real1_out, imag1_out,
    output logic signed [WIDTH-1:0] real2_out, imag2_out,
    output logic signed [WIDTH-1:0] real3_out, imag3_out
);
    // Sample storage
    logic signed [WIDTH-1:0] real_mem[0:3];
    logic signed [WIDTH-1:0] imag_mem[0:3];
    
    // Initialize arrays properly
    integer i;
    always_ff @(posedge clk or posedge rst) begin
        if (rst) begin
            for (i = 0; i < 4; i = i + 1) begin
                real_mem[i] <= 0;
                imag_mem[i] <= 0;
            end
        end else if (ena && load_pulse) begin
            real_mem[addr] <= $signed(data_in[7:4]) << 4;
            imag_mem[addr] <= $signed(data_in[3:0]) << 4;
        end
    end
    
    // Continuous assignments for outputs
    assign real0_out = real_mem[0];
    assign imag0_out = imag_mem[0];
    assign real1_out = real_mem[1];
    assign imag1_out = imag_mem[1];
    assign real2_out = real_mem[2];
    assign imag2_out = imag_mem[2];
    assign real3_out = real_mem[3];
    assign imag3_out = imag_mem[3];
endmodule

test/memory_ctrl/memory_ctrl_tb.sv
`default_nettype none
`timescale 1ns / 1ps

module memory_ctrl_tb (
    // Control Signals
    input  logic clk,
    input  logic rst,
    input  logic ena,
    input  logic load_pulse,

    // Write Port
    input  logic [1:0] addr,
    input  logic [7:0] data_in,

    // Read Outputs
    output logic signed [7:0] real0_out, imag0_out,
    output logic signed [7:0] real1_out, imag1_out,
    output logic signed [7:0] real2_out, imag2_out,
    output logic signed [7:0] real3_out, imag3_out
);

    // Dump the signals to a VCD file for debugging
    string vcd_name;
    initial begin
`ifdef VCD_PATH
        vcd_name = `VCD_PATH;
`else
        vcd_name = {"memory_ctrl_tb_", `TIMESTAMP, ".vcd"};
`endif
        $dumpfile(vcd_name);
        $dumpvars(0, memory_ctrl_tb);
        #1;
    end

    // Instantiate the memory controller (DUT)
    memory_ctrl #(
        .WIDTH(8)
    ) dut (
        .clk(clk),
        .rst(rst),
        .ena(ena),
        .load_pulse(load_pulse),
        .addr(addr),
        .data_in(data_in),
        .real0_out(real0_out),
        .imag0_out(imag0_out),
        .real1_out(real1_out),
        .imag1_out(imag1_out),
        .real2_out(real2_out),
        .imag2_out(imag2_out),
        .real3_out(real3_out),
        .imag3_out(imag3_out)
    );

endmodule

test/memory_ctrl/wave/memory_ctrl_tb_20250703_00:10:44.vcd
$date
	Thu Jul  3 00:10:49 2025
$end
$version
	Icarus Verilog
$end
$timescale
	1ps
$end
$scope module memory_ctrl_tb $end
$var wire 2 ! addr [1:0] $end
$var wire 1 " clk $end
$var wire 8 # data_in [7:0] $end
$var wire 1 $ ena $end
$var wire 1 % load_pulse $end
$var wire 1 & rst $end
$var wire 8 ' real3_out [7:0] $end
$var wire 8 ( real2_out [7:0] $end
$var wire 8 ) real1_out [7:0] $end
$var wire 8 * real0_out [7:0] $end
$var wire 8 + imag3_out [7:0] $end
$var wire 8 , imag2_out [7:0] $end
$var wire 8 - imag1_out [7:0] $end
$var wire 8 . imag0_out [7:0] $end
$scope module dut $end
$var wire 2 / addr [1:0] $end
$var wire 1 " clk $end
$var wire 8 0 data_in [7:0] $end
$var wire 1 $ ena $end
$var wire 8 1 imag0_out [7:0] $end
$var wire 8 2 imag1_out [7:0] $end
$var wire 8 3 imag2_out [7:0] $end
$var wire 8 4 imag3_out [7:0] $end
$var wire 1 % load_pulse $end
$var wire 8 5 real0_out [7:0] $end
$var wire 8 6 real1_out [7:0] $end
$var wire 8 7 real2_out [7:0] $end
$var wire 8 8 real3_out [7:0] $end
$var wire 1 & rst $end
$var integer 32 9 i [31:0] $end
$upscope $end
$upscope $end
$enddefinitions $end
#0
$dumpvars
b100 9
b0 8
b0 7
b0 6
b0 5
b0 4
b0 3
b0 2
b0 1
b10010 0
b1 /
b0 .
b0 -
b0 ,
b0 +
b0 *
b0 )
b0 (
b0 '
1&
0%
1$
b10010 #
1"
b1 !
$end
#5000
0&
0"
#10000
1"
#10001
1%
#15001
0"
#20001
b100 9
1&
0%
b0 -
b0 2
b0 )
b0 6
1"
#25001
0&
0"
#30001
b10010110 #
b10010110 0
b10 !
b10 /
1%
1"
#35001
0"
#40001
0%
b1100000 ,
b1100000 3
b10010000 (
b10010000 7
1"
#41002
b10010 #
b10010 0
b1 !
b1 /
1%
#46002
0"
#51002
b0 ,
b0 3
b0 (
b0 7
b100 9
1&
0%
b0 -
b0 2
b0 )
b0 6
1"
#56002
0&
0"
#61002
b11111111 #
b11111111 0
b11 !
b11 /
1%
0$
1"
#66002
0"
#71002
0%
1"
#72002
1$
#76002
0"
#81002
1"
#82003
b10010 #
b10010 0
b1 !
b1 /
1%
#87003
0"
#92003
b100 9
1&
0%
b0 -
b0 2
b0 )
b0 6
1"
#97003
0&
0"
#102003
1%
b1110111 #
b1110111 0
b0 !
b0 /
1"
#107003
0"
#112003
0%
b1110000 .
b1110000 1
b1110000 *
b1110000 5
1"
