src/memory_ctrl.sv
module memory_ctrl #(
    parameter WIDTH = 8
)(
    input  logic clk, rst, ena,
    input  logic load_pulse,
    input  logic [1:0] addr,
    input  logic [7:0] data_in,
    output logic signed [WIDTH-1:0] real0_out, imag0_out,
    output logic signed [WIDTH-1:0] real1_out, imag1_out,
    output logic signed [WIDTH-1:0] real2_out, imag2_out,
    output logic signed [WIDTH-1:0] real3_out, imag3_out
);
    // Sample storage
    logic signed [WIDTH-1:0] real_mem[0:3];
    logic signed [WIDTH-1:0] imag_mem[0:3];
    
    // Initialize arrays properly
    integer i;
    always_ff @(posedge clk or posedge rst) begin
        if (rst) begin
            for (i = 0; i < 4; i = i + 1) begin
                real_mem[i] <= 0;
                imag_mem[i] <= 0;
            end
        end else if (ena && load_pulse) begin
            real_mem[addr] <= $signed(data_in[7:4]) << 4;
            imag_mem[addr] <= $signed(data_in[3:0]) << 4;
        end
    end
    
    // Continuous assignments for outputs
    assign real0_out = real_mem[0];
    assign imag0_out = imag_mem[0];
    assign real1_out = real_mem[1];
    assign imag1_out = imag_mem[1];
    assign real2_out = real_mem[2];
    assign imag2_out = imag_mem[2];
    assign real3_out = real_mem[3];
    assign imag3_out = imag_mem[3];
endmodule

test/memory_ctrl/memory_ctrl_tb.sv
`default_nettype none
`timescale 1ns / 1ps

module memory_ctrl_tb (
    // Control Signals
    input  logic clk,
    input  logic rst,
    input  logic ena,
    input  logic load_pulse,

    // Write Port
    input  logic [1:0] addr,
    input  logic [7:0] data_in,

    // Read Outputs
    output logic signed [7:0] real0_out, imag0_out,
    output logic signed [7:0] real1_out, imag1_out,
    output logic signed [7:0] real2_out, imag2_out,
    output logic signed [7:0] real3_out, imag3_out
);

logic [7:0] current_test_id = 0;

    // Dump the signals to a VCD file for debugging
    string vcd_name;
    initial begin
`ifdef VCD_PATH
        vcd_name = `VCD_PATH;
`else
        vcd_name = {"memory_ctrl_tb_", `TIMESTAMP, ".vcd"};
`endif
        $dumpfile(vcd_name);
        $dumpvars(0, memory_ctrl_tb);
        #1;
    end

    // Instantiate the memory controller (DUT)
    memory_ctrl #(
        .WIDTH(8)
    ) dut (
        .clk(clk),
        .rst(rst),
        .ena(ena),
        .load_pulse(load_pulse),
        .addr(addr),
        .data_in(data_in),
        .real0_out(real0_out),
        .imag0_out(imag0_out),
        .real1_out(real1_out),
        .imag1_out(imag1_out),
        .real2_out(real2_out),
        .imag2_out(imag2_out),
        .real3_out(real3_out),
        .imag3_out(imag3_out)
    );

endmodule

test/memory_ctrl/wave/memory_ctrl_tb_20250707_22:35:56.vcd
$date
	Mon Jul  7 22:35:59 2025
$end
$version
	Icarus Verilog
$end
$timescale
	1ps
$end
$scope module memory_ctrl_tb $end
$var wire 2 ! addr [1:0] $end
$var wire 1 " clk $end
$var wire 8 # data_in [7:0] $end
$var wire 1 $ ena $end
$var wire 1 % load_pulse $end
$var wire 1 & rst $end
$var wire 8 ' real3_out [7:0] $end
$var wire 8 ( real2_out [7:0] $end
$var wire 8 ) real1_out [7:0] $end
$var wire 8 * real0_out [7:0] $end
$var wire 8 + imag3_out [7:0] $end
$var wire 8 , imag2_out [7:0] $end
$var wire 8 - imag1_out [7:0] $end
$var wire 8 . imag0_out [7:0] $end
$var reg 8 / current_test_id [7:0] $end
$scope module dut $end
$var wire 2 0 addr [1:0] $end
$var wire 1 " clk $end
$var wire 8 1 data_in [7:0] $end
$var wire 1 $ ena $end
$var wire 8 2 imag0_out [7:0] $end
$var wire 8 3 imag1_out [7:0] $end
$var wire 8 4 imag2_out [7:0] $end
$var wire 8 5 imag3_out [7:0] $end
$var wire 1 % load_pulse $end
$var wire 8 6 real0_out [7:0] $end
$var wire 8 7 real1_out [7:0] $end
$var wire 8 8 real2_out [7:0] $end
$var wire 8 9 real3_out [7:0] $end
$var wire 1 & rst $end
$var parameter 32 : WIDTH $end
$var integer 32 ; i [31:0] $end
$upscope $end
$upscope $end
$enddefinitions $end
$comment Show the parameter values. $end
$dumpall
b1000 :
$end
#0
$dumpvars
b100 ;
b0 9
b0 8
b0 7
b0 6
b0 5
b0 4
b0 3
b0 2
b10010 1
b1 0
b1 /
b0 .
b0 -
b0 ,
b0 +
b0 *
b0 )
b0 (
b0 '
1&
0%
1$
b10010 #
1"
b1 !
$end
#5000
0&
0"
#10000
1"
#10001
1%
#15001
0"
#20001
b100 ;
1&
0%
b0 -
b0 3
b0 )
b0 7
1"
#25001
0&
0"
#30001
b10010110 #
b10010110 1
b10 !
b10 0
1%
b10 /
1"
#35001
0"
#40001
0%
b1100000 ,
b1100000 4
b10010000 (
b10010000 8
1"
#41002
b10010 #
b10010 1
b1 !
b1 0
1%
b1 /
#46002
0"
#51002
b0 ,
b0 4
b0 (
b0 8
b100 ;
1&
0%
b0 -
b0 3
b0 )
b0 7
1"
#56002
0&
0"
#61002
b11111111 #
b11111111 1
b11 !
b11 0
1%
0$
b11 /
1"
#66002
0"
#71002
0%
1"
#72002
1$
#76002
0"
#81002
1"
#82003
b10010 #
b10010 1
b1 !
b1 0
1%
b1 /
#87003
0"
#92003
b100 ;
1&
0%
b0 -
b0 3
b0 )
b0 7
1"
#97003
0&
0"
#102003
b11010010 #
b11010010 1
b100 /
1"
#107003
0"
#112003
1"
#113003
b1100010 #
b1100010 1
b10 !
b10 0
#117003
0"
#122003
1"
#123003
1%
b10011000 #
b10011000 1
b0 !
b0 0
#127003
0"
#132003
0%
b10000000 .
b10000000 2
b10010000 *
b10010000 6
1"
#133003
b10010110 #
b10010110 1
b1 !
b1 0
#137003
0"
#142003
1"
#143003
1%
b1010001 #
b1010001 1
#147003
0"
#152003
0%
b10000 -
b10000 3
b1010000 )
b1010000 7
1"
#153003
1%
b1000 #
b1000 1
b11 !
b11 0
#157003
0"
#162003
0%
b10000000 +
b10000000 5
1"
#163003
b101001 #
b101001 1
b0 !
b0 0
#167003
0"
#172003
1"
#173003
1%
b11011000 #
b11011000 1
b1 !
b1 0
#177003
0"
#182003
0%
b10000000 -
b10000000 3
b11010000 )
b11010000 7
1"
#183003
1%
b1000011 #
b1000011 1
b0 !
b0 0
#187003
0"
#192003
0%
b110000 .
b110000 2
b1000000 *
b1000000 6
1"
#193003
b10110100 #
b10110100 1
b10 !
b10 0
#197003
0"
#202003
1"
#203003
b11110010 #
b11110010 1
b11 !
b11 0
#207003
0"
#212003
1"
#213003
b110101 #
b110101 1
#217003
0"
#222003
1"
#223003
1%
b11111011 #
b11111011 1
b10 !
b10 0
#227003
0"
#232003
0%
b10110000 ,
b10110000 4
b11110000 (
b11110000 8
1"
#233003
b10001000 #
b10001000 1
b11 !
b11 0
#237003
0"
#242003
1"
#243003
b1010001 #
b1010001 1
b0 !
b0 0
#247003
0"
#252003
1"
#253003
1%
b11111110 #
b11111110 1
b10 !
b10 0
#257003
0"
#262003
0%
b11100000 ,
b11100000 4
1"
#263003
1%
b10001000 #
b10001000 1
b1 !
b1 0
#267003
0"
#272003
0%
b10000000 )
b10000000 7
1"
#273003
1%
b1011100 #
b1011100 1
b11 !
b11 0
#277003
0"
#282003
0%
b11000000 +
b11000000 5
b1010000 '
b1010000 9
1"
#283003
b1011 #
b1011 1
b0 !
b0 0
#287003
0"
#292003
1"
#293003
1%
b1100101 #
b1100101 1
#297003
0"
#302003
0%
b1010000 .
b1010000 2
b1100000 *
b1100000 6
1"
#303003
b11000001 #
b11000001 1
b11 !
b11 0
#307003
0"
#312003
1"
#313003
1%
b11110001 #
b11110001 1
b10 !
b10 0
#317003
0"
#322003
0%
b10000 ,
b10000 4
1"
#323003
1%
b1100011 #
b1100011 1
b1 !
b1 0
#327003
0"
#332003
0%
b110000 -
b110000 3
b1100000 )
b1100000 7
1"
#333003
b11110010 #
b11110010 1
#337003
0"
#342003
1"
#343003
1%
b11111110 #
b11111110 1
b11 !
b11 0
#347003
0"
#352003
0%
b11100000 +
b11100000 5
b11110000 '
b11110000 9
1"
#353003
1%
b11010 #
b11010 1
b0 !
b0 0
#357003
0"
#362003
0%
b10100000 .
b10100000 2
b10000 *
b10000 6
1"
#363003
b111100 #
b111100 1
#367003
0"
#372003
1"
#373003
b1101000 #
b1101000 1
b11 !
b11 0
#377003
0"
#382003
1"
#383003
b100101 #
b100101 1
b1 !
b1 0
#387003
0"
#392003
1"
#393003
1%
b11101001 #
b11101001 1
b10 !
b10 0
#397003
0"
#402003
0%
b10010000 ,
b10010000 4
b11100000 (
b11100000 8
1"
#403003
1%
b11110001 #
b11110001 1
b1 !
b1 0
#407003
0"
#412003
0%
b10000 -
b10000 3
b11110000 )
b11110000 7
1"
#413003
1%
b10010 #
b10010 1
b0 !
b0 0
#417003
0"
#422003
0%
b100000 .
b100000 2
1"
#423003
1%
b11011100 #
b11011100 1
b11 !
b11 0
#427003
0"
#432003
0%
b11000000 +
b11000000 5
b11010000 '
b11010000 9
1"
#433003
1%
b1100100 #
b1100100 1
b0 !
b0 0
#437003
0"
#442003
0%
b1000000 .
b1000000 2
b1100000 *
b1100000 6
1"
#443003
b110101 #
b110101 1
b11 !
b11 0
#447003
0"
#452003
1"
#453003
1%
b10101000 #
b10101000 1
b0 !
b0 0
#457003
0"
#462003
0%
b10000000 .
b10000000 2
b10100000 *
b10100000 6
1"
#463003
b10100000 #
b10100000 1
b11 !
b11 0
#467003
0"
#472003
1"
#473003
b10110011 #
b10110011 1
b0 !
b0 0
#477003
0"
#482003
1"
#483003
1%
b1111011 #
b1111011 1
b10 !
b10 0
#487003
0"
#492003
0%
b10110000 ,
b10110000 4
b1110000 (
b1110000 8
1"
#493003
1%
b1001010 #
b1001010 1
b1 !
b1 0
#497003
0"
#502003
0%
b10100000 -
b10100000 3
b1000000 )
b1000000 7
1"
#503003
1%
b1010101 #
b1010101 1
b0 !
b0 0
#507003
0"
#512003
0%
b1010000 .
b1010000 2
b1010000 *
b1010000 6
1"
#513003
1%
b11000101 #
b11000101 1
b1 !
b1 0
#517003
0"
#522003
0%
b1010000 -
b1010000 3
b11000000 )
b11000000 7
1"
#523003
b0 #
b0 1
#527003
0"
#532003
1"
#533003
1%
b10011011 #
b10011011 1
#537003
0"
#542003
0%
b10110000 -
b10110000 3
b10010000 )
b10010000 7
1"
#543003
1%
b10101000 #
b10101000 1
b0 !
b0 0
#547003
0"
#552003
0%
b10000000 .
b10000000 2
b10100000 *
b10100000 6
1"
#553003
b11011011 #
b11011011 1
b11 !
b11 0
#557003
0"
#562003
1"
#563003
b10110 #
b10110 1
#567003
0"
#572003
1"
#573003
b0 #
b0 1
#577003
0"
#582003
1"
#583003
b11101000 #
b11101000 1
b0 !
b0 0
#587003
0"
#592003
1"
#593003
1%
b11000 #
b11000 1
#597003
0"
#602003
0%
b10000 *
b10000 6
1"
