test/butterfly_unit/butterfly_golden.sv
module butterfly_golden #( WIDTH = 8 ) (
    input signed  [ WIDTH - 1 : 0 ] A,
    input signed  [ WIDTH - 1 : 0 ] B,
    input signed  [ WIDTH - 1 : 0 ] W,
    output signed [ WIDTH - 1 : 0 ] plus, // A + W*B
    output signed [ WIDTH - 1 : 0 ] minus // A - W*B
);

    wire [ WIDTH/2 - 1 : 0 ] w_real;
    wire [ WIDTH/2 - 1 : 0 ] w_imag;
    wire [ WIDTH/2 - 1 : 0 ] b_real;
    wire [ WIDTH/2 - 1 : 0 ] b_imag;
    
    assign w_real = W[ WIDTH - 1   : WIDTH/2 ] ;
    assign w_imag = W[ WIDTH/2 - 1 : 0 ];
    assign b_real = B[ WIDTH - 1   : WIDTH/2 ];
    assign b_imag = B[ WIDTH/2 - 1 : 0 ];
    
    wire [ WIDTH - 1 : 0 ] product;

    wire [ WIDTH - 1 : 0 ] product_real;
    wire [ WIDTH - 1 : 0 ] product_imag;
    
    wire [ WIDTH/2 - 1 : 0] product_real_trunc;
    wire [ WIDTH/2 - 1 : 0] product_imag_trunc;

    assign product_real = (w_real * b_real) - (w_imag * b_imag);
    assign product_imag = (w_imag * b_real) + (w_real * b_imag);

    assign product_real_trunc = product_real[ WIDTH - 1 : WIDTH - 1 - WIDTH/2 ];
    assign product_imag_trunc = product_imag[ WIDTH - 1 : WIDTH - 1 - WIDTH/2 ];

    assign plus  = {
        A[ WIDTH - 1 : WIDTH/2 ] + product_real_trunc,
        A[ WIDTH/2 - 1 : 0] + product_imag_trunc
    };
    assign minus = {
        A[ WIDTH - 1 : WIDTH/2 ] - product_real_trunc,
        A[ WIDTH/2 - 1 : 0] - product_imag_trunc
    };
endmodule

src/butterfly_unit.sv
module butterfly_unit #(parameter WIDTH = 8) (
    input  logic        clk,
    input  logic        rst,
    input  logic        en,
    input  logic signed [WIDTH-1:0] A,
    input  logic signed [WIDTH-1:0] B,
    input  logic signed [WIDTH-1:0] T,
    output logic signed [WIDTH-1:0] Pos,
    output logic signed [WIDTH-1:0] Neg,
    output logic        valid
);

    localparam HALF_WIDTH = WIDTH / 2;

    // Unpack inputs (same as golden model)
    wire [HALF_WIDTH-1:0] a_real = A[WIDTH-1:HALF_WIDTH];
    wire [HALF_WIDTH-1:0] a_imag = A[HALF_WIDTH-1:0];
    wire [HALF_WIDTH-1:0] b_real = B[WIDTH-1:HALF_WIDTH];
    wire [HALF_WIDTH-1:0] b_imag = B[HALF_WIDTH-1:0];
    wire [HALF_WIDTH-1:0] t_real = T[WIDTH-1:HALF_WIDTH];
    wire [HALF_WIDTH-1:0] t_imag = T[HALF_WIDTH-1:0];

    // Complex multiplication (same as golden model)
    wire [WIDTH-1:0] product_real = (t_real * b_real) - (t_imag * b_imag);
    wire [WIDTH-1:0] product_imag = (t_imag * b_real) + (t_real * b_imag);
    
    // Truncation (same as golden model)
    wire [HALF_WIDTH-1:0] product_real_trunc = product_real[WIDTH-1 : WIDTH-1-HALF_WIDTH];
    wire [HALF_WIDTH-1:0] product_imag_trunc = product_imag[WIDTH-1 : WIDTH-1-HALF_WIDTH];

    // Combinational results (same as golden model)
    wire [WIDTH-1:0] pos_comb = { a_real + product_real_trunc, a_imag + product_imag_trunc };
    wire [WIDTH-1:0] neg_comb = { a_real - product_real_trunc, a_imag - product_imag_trunc };

    // Sequential output stage - only update when enabled
    always_ff @(posedge clk) begin
        if (rst) begin
            Pos   <= '0;
            Neg   <= '0;
            valid <= 1'b0;
        end else if (en) begin
            Pos   <= pos_comb;
            Neg   <= neg_comb;
            valid <= 1'b1;
        end else begin
            valid <= 1'b0;
        end
    end

endmodule

test/butterfly_unit/butterfly_tb.sv
`default_nettype none
`timescale 1ns / 1ps

module butterfly_tb (
  output logic [7:0] plus,
  output logic [7:0] minus
);

  // Dump the signals to a VCD file
  string vcd_name;
  initial begin
`ifdef VCD_PATH
    vcd_name = `VCD_PATH;
`else
    vcd_name = {"butterfly_tb_", `TIMESTAMP, ".vcd"};
`endif
    $dumpfile(vcd_name);
    $dumpvars(0, butterfly_tb);
    #1;
  end

  // Clock and control signals
  reg clk;
  reg rst;
  reg en;
  
  // Input data signals (8-bit packed complex)
  reg [7:0] A;
  reg [7:0] B;
  reg [7:0] T;
  
  // Output signals
  wire [7:0] Pos;
  wire [7:0] Neg;
  wire        valid;

  // Instantiate the butterfly unit (DUT)
  butterfly_unit dut (
      .clk(clk),
      .rst(rst),
      .en(en),
      .A(A),
      .B(B),
      .T(T),
      .Pos(Pos),
      .Neg(Neg),
      .valid(valid)
  );

  // Instantiate the golden model for comparison
  butterfly_golden #(.WIDTH(8)) golden_model (
      .A(A),
      .B(B),
      .W(T),      // T maps to W
      .plus(plus),
      .minus(minus)
  );

endmodule

test/butterfly_unit/wave/butterfly_tb_20250623_02:38:30.vcd
$date
	Mon Jun 23 02:38:32 2025
$end
$version
	Icarus Verilog
$end
$timescale
	1ps
$end
$scope module butterfly_tb $end
$var wire 1 ! valid $end
$var wire 8 " plus [7:0] $end
$var wire 8 # minus [7:0] $end
$var wire 8 $ Pos [7:0] $end
$var wire 8 % Neg [7:0] $end
$var reg 8 & A [7:0] $end
$var reg 8 ' B [7:0] $end
$var reg 8 ( T [7:0] $end
$var reg 1 ) clk $end
$var reg 1 * en $end
$var reg 1 + rst $end
$scope module dut $end
$var wire 8 , A [7:0] $end
$var wire 8 - B [7:0] $end
$var wire 8 . T [7:0] $end
$var wire 1 ) clk $end
$var wire 1 * en $end
$var wire 1 + rst $end
$var wire 4 / t_real [3:0] $end
$var wire 4 0 t_imag [3:0] $end
$var wire 4 1 product_real_trunc [3:0] $end
$var wire 8 2 product_real [7:0] $end
$var wire 4 3 product_imag_trunc [3:0] $end
$var wire 8 4 product_imag [7:0] $end
$var wire 8 5 pos_comb [7:0] $end
$var wire 8 6 neg_comb [7:0] $end
$var wire 4 7 b_real [3:0] $end
$var wire 4 8 b_imag [3:0] $end
$var wire 4 9 a_real [3:0] $end
$var wire 4 : a_imag [3:0] $end
$var parameter 32 ; HALF_WIDTH $end
$var parameter 32 < WIDTH $end
$var reg 8 = Neg [7:0] $end
$var reg 8 > Pos [7:0] $end
$var reg 1 ! valid $end
$upscope $end
$scope module golden_model $end
$var wire 8 ? A [7:0] $end
$var wire 8 @ B [7:0] $end
$var wire 8 A W [7:0] $end
$var wire 4 B w_real [3:0] $end
$var wire 4 C w_imag [3:0] $end
$var wire 4 D product_real_trunc [3:0] $end
$var wire 8 E product_real [7:0] $end
$var wire 4 F product_imag_trunc [3:0] $end
$var wire 8 G product_imag [7:0] $end
$var wire 8 H plus [7:0] $end
$var wire 8 I minus [7:0] $end
$var wire 4 J b_real [3:0] $end
$var wire 4 K b_imag [3:0] $end
$var parameter 32 L WIDTH $end
$upscope $end
$upscope $end
$enddefinitions $end
$comment Show the parameter values. $end
$dumpall
b1000 L
b1000 <
b100 ;
$end
#0
$dumpvars
bx K
bx J
bx I
bx H
bx G
bx F
bx E
bx D
bx C
bx B
bx A
bx @
bx ?
b0 >
b0 =
bx :
bx 9
bx 8
bx 7
bx 6
bx 5
bx 4
bx 3
bx 2
bx 1
bx 0
bx /
bx .
bx -
bx ,
0+
x*
1)
bx (
bx '
bx &
b0 %
b0 $
bx #
bx "
0!
$end
#5000
0)
#10000
b0 1
b10001 5
b10001 6
b0 3
b0 D
b10001 "
b10001 H
b10001 #
b10001 I
b0 F
b10 2
b10 4
b1 /
b0 0
b10 E
b10 G
b1 B
b0 C
b10 7
b10 8
b10 J
b10 K
b1 9
b1 :
1*
b10000 (
b10000 .
b10000 A
b100010 '
b100010 -
b100010 @
b10001 &
b10001 ,
b10001 ?
1)
#15000
0)
#20000
1!
b10001 %
b10001 =
b10001 $
b10001 >
1)
#25000
0)
#30000
1)
#35000
0)
#40000
1)
#45000
0)
#50000
1)
#55000
0)
#60000
1)
#65000
0)
#70000
1)
#75000
0)
#80000
1)
#85000
0)
#90000
1)
#95000
0)
#100000
1)
#105000
0)
#110000
1)
#115000
0)
#120000
1)
#125000
0)
#130000
1)
#135000
0)
#140000
1)
#145000
0)
#150000
1)
#155000
0)
#160000
1)
#165000
0)
#170000
1)
#175000
0)
#180000
1)
#185000
0)
#190000
1)
#195000
0)
#200000
1)
#205000
0)
#210000
0*
1)
#215000
0)
#220000
0!
1)
#225000
0)
#230000
b1 5
b100001 6
b1111 1
b1 "
b1 H
b100001 #
b100001 I
b1111 D
b0 /
b11111110 2
b10 4
b1 0
b0 B
b11111110 E
b10 G
b1 C
1*
b1 (
b1 .
b1 A
1)
#235000
0)
#240000
1!
b100001 %
b100001 =
b1 $
b1 >
1)
#245000
0)
#250000
1)
#255000
0)
#260000
1)
#265000
0)
#270000
1)
#275000
0)
#280000
1)
#285000
0)
#290000
1)
#295000
0)
#300000
1)
#305000
0)
#310000
1)
#315000
0)
#320000
1)
#325000
0)
#330000
1)
#335000
0)
#340000
1)
#345000
0)
#350000
1)
#355000
0)
#360000
1)
#365000
0)
#370000
1)
#375000
0)
#380000
1)
#385000
0)
#390000
1)
#395000
0)
#400000
1)
#405000
0)
#410000
1)
#415000
0)
#420000
1)
#425000
0)
#430000
0*
1)
#435000
0)
#440000
0!
1)
#445000
0)
#450000
b11 3
b1000100 5
b11101110 6
b11 1
b11 F
b1000100 "
b1000100 H
b11101110 #
b11101110 I
b11 D
b1111 /
b11110 2
b11110 4
b0 0
b1111 B
b11110 E
b11110 G
b0 C
1*
b11110000 (
b11110000 .
b11110000 A
1)
#455000
0)
#460000
1!
b11101110 %
b11101110 =
b1000100 $
b1000100 >
1)
#465000
0)
#470000
1)
#475000
0)
#480000
1)
#485000
0)
#490000
1)
#495000
0)
#500000
1)
#505000
0)
#510000
1)
#515000
0)
#520000
1)
#525000
0)
#530000
1)
#535000
0)
#540000
1)
#545000
0)
#550000
1)
#555000
0)
#560000
1)
#565000
0)
#570000
1)
#575000
0)
#580000
1)
#585000
0)
#590000
1)
#595000
0)
#600000
1)
#605000
0)
#610000
1)
#615000
0)
#620000
1)
#625000
0)
#630000
1)
#635000
0)
#640000
1)
#645000
0)
#650000
0*
1)
#655000
0)
#660000
0!
1)
#665000
0)
#670000
b1111 1
b1 3
b1111 D
b1 F
b10 /
b1 0
b10 B
b1 C
b11111110 2
b1 7
b1001 4
b100 8
b11111110 E
b1 J
b1001 G
b100 K
b11 9
b100011 5
b1000001 6
b10 :
b100011 "
b100011 H
b1000001 #
b1000001 I
1*
b100001 (
b100001 .
b100001 A
b10100 '
b10100 -
b10100 @
b110010 &
b110010 ,
b110010 ?
1)
#675000
0)
#680000
1!
b1000001 %
b1000001 =
b100011 $
b100011 >
1)
#685000
0)
#690000
1)
#695000
0)
#700000
1)
#705000
0)
#710000
1)
#715000
0)
#720000
1)
#725000
0)
#730000
1)
#735000
0)
#740000
1)
#745000
0)
#750000
1)
#755000
0)
#760000
1)
#765000
0)
#770000
1)
#775000
0)
#780000
1)
#785000
0)
#790000
1)
#795000
0)
#800000
1)
#805000
0)
#810000
1)
#815000
0)
#820000
1)
#825000
0)
#830000
1)
#835000
0)
#840000
1)
#845000
0)
#850000
1)
#855000
0)
#860000
1)
#865000
0)
#870000
0*
1)
#875000
0)
#880000
0!
1)
#885000
0)
#890000
1)
#890001
1+
#895001
0)
#900001
0+
b0 %
b0 =
b0 $
b0 >
1)
#905001
0)
#910001
b0 1
b0 3
b0 D
b0 F
b1 /
b0 0
b1 B
b0 C
b10 7
b10 2
b10 4
b10 8
b10 J
b10 E
b10 G
b10 K
b1 9
b10001 5
b10001 6
b1 :
b10001 "
b10001 H
b10001 #
b10001 I
b10000 (
b10000 .
b10000 A
b100010 '
b100010 -
b100010 @
b10001 &
b10001 ,
b10001 ?
1)
#915001
0)
#920001
1)
#925001
0)
#930001
1)
#935001
0)
#940001
1*
1)
#945001
0)
#950001
1!
b10001 %
b10001 =
b10001 $
b10001 >
1)
#955001
0)
#960001
1)
#960002
1+
#965002
0)
#970002
0+
0!
b0 %
b0 =
b0 $
b0 >
1)
#975002
0)
#980002
1!
b10001 %
b10001 =
b10001 $
b10001 >
1)
#985002
0)
#990002
1)
#995002
0)
#1000002
1)
#1005002
0)
#1010002
1)
#1015002
0)
#1020002
1)
#1025002
0)
#1030002
1)
#1035002
0)
#1040002
1)
#1045002
0)
#1050002
1)
#1055002
0)
#1060002
1)
#1065002
0)
#1070002
1)
#1075002
0)
#1080002
1)
#1085002
0)
#1090002
1)
#1095002
0)
#1100002
1)
#1105002
0)
#1110002
1)
#1115002
0)
#1120002
1)
#1125002
0)
#1130002
1)
#1135002
0)
#1140002
1)
#1145002
0)
#1150002
1)
#1155002
0)
#1160002
1)
#1165002
0)
#1170002
1)
#1175002
0)
#1180002
1+
1)
#1185002
0)
#1190002
0!
b0 %
b0 =
b0 $
b0 >
1)
#1195002
0)
#1200002
1)
#1205002
0)
#1210002
1)
#1215002
0)
#1220002
1)
#1225002
0)
#1230002
1)
#1235002
0)
#1240002
1)
#1245002
0)
#1250002
1)
#1255002
0)
#1260002
1)
#1265002
0)
#1270002
1)
#1275002
0)
#1280002
0+
1)
#1285002
0)
#1290002
1!
b10001 %
b10001 =
b10001 $
b10001 >
1)
#1290003
1+
#1295003
0)
#1300003
0+
0!
b0 %
b0 =
b0 $
b0 >
1)
#1305003
0)
#1310003
1!
b10001 %
b10001 =
b10001 $
b10001 >
1)
#1315003
0)
#1320003
b1111 1
b1111 D
b0 /
b1 0
b0 B
b1 C
b11111101 2
b11 7
b11 4
b11 8
b11111101 E
b11 J
b11 G
b11 K
b10 9
b10010 5
b110010 6
b10 :
b10010 "
b10010 H
b110010 #
b110010 I
b1 (
b1 .
b1 A
b110011 '
b110011 -
b110011 @
b100010 &
b100010 ,
b100010 ?
1)
#1325003
0)
#1330003
b111 3
b111 1
b111 F
b111 D
b1111 /
b0 0
b1111 B
b0 C
b111100 4
b100 7
b111100 2
b100 8
b111100 G
b100 J
b111100 E
b100 K
b11 9
b10101010 5
b11001100 6
b11 :
b10101010 "
b10101010 H
b11001100 #
b11001100 I
b11110000 (
b11110000 .
b11110000 A
b1000100 '
b1000100 -
b1000100 @
b110011 &
b110011 ,
b110011 ?
b110010 %
b110010 =
b10010 $
b10010 >
1)
#1335003
0)
#1340003
b0 1
b1 3
b0 D
b1 F
b1 /
b1 0
b1 B
b1 C
b0 2
b101 7
b1010 4
b101 8
b0 E
b101 J
b1010 G
b101 K
b100 9
b1000101 5
b1000011 6
b100 :
b1000101 "
b1000101 H
b1000011 #
b1000011 I
b10001 (
b10001 .
b10001 A
b1010101 '
b1010101 -
b1010101 @
b1000100 &
b1000100 ,
b1000100 ?
b11001100 %
b11001100 =
b10101010 $
b10101010 >
1)
#1345003
0)
#1350003
b1011 3
b1011 F
b100 1
b100 D
b0 /
b1111 0
b0 B
b1111 C
b110 7
b10100110 2
b1011010 4
b110 8
b110 J
b10100110 E
b1011010 G
b110 K
b101 9
b10010000 5
b11010 6
b101 :
b10010000 "
b10010000 H
b11010 #
b11010 I
b1111 (
b1111 .
b1111 A
b1100110 '
b1100110 -
b1100110 @
b1010101 &
b1010101 ,
b1010101 ?
b1000011 %
b1000011 =
b1000101 $
b1000101 >
1)
#1355003
0)
#1360003
0*
b11010 %
b11010 =
b10010000 $
b10010000 >
1)
#1365003
0)
#1370003
0!
1)
#1375003
0)
#1380003
1)
#1380004
1+
#1385004
0)
#1390004
0+
b0 %
b0 =
b0 $
b0 >
1)
#1395004
0)
#1400004
b1100 3
b0 1
b1100 F
b0 D
b111 /
b111 0
b111 B
b111 C
b1100010 4
b111 7
b0 2
b111 8
b1100010 G
b111 J
b0 E
b111 K
b111 9
b1110011 5
b1111011 6
b111 :
b1110011 "
b1110011 H
b1111011 #
b1111011 I
1*
b1110111 (
b1110111 .
b1110111 A
b1110111 '
b1110111 -
b1110111 @
b1110111 &
b1110111 ,
b1110111 ?
1)
#1405004
0)
#1410004
1!
b1111011 %
b1111011 =
b1110011 $
b1110011 >
1)
#1415004
0)
#1420004
b0 3
b0 F
b1000 /
b1000 0
b1000 B
b1000 C
b1000 7
b0 2
b10000000 4
b1000 8
b1000 J
b0 E
b10000000 G
b1000 K
b1000 9
b10001000 5
b10001000 6
b1000 :
b10001000 "
b10001000 H
b10001000 #
b10001000 I
b10001000 (
b10001000 .
b10001000 A
b10001000 '
b10001000 -
b10001000 @
b10001000 &
b10001000 ,
b10001000 ?
1)
#1425004
0)
#1430004
b10001000 %
b10001000 =
b10001000 $
b10001000 >
1)
#1435004
0)
#1440004
b1 /
b0 0
b1 B
b0 C
b111 7
b111 2
b111 4
b111 8
b111 J
b111 E
b111 G
b111 K
b111 9
b1110111 5
b1110111 6
b111 :
b1110111 "
b1110111 H
b1110111 #
b1110111 I
b10000 (
b10000 .
b10000 A
b1110111 '
b1110111 -
b1110111 @
b1110111 &
b1110111 ,
b1110111 ?
1)
#1445004
0)
#1450004
b1110111 %
b1110111 =
b1110111 $
b1110111 >
1)
#1455004
0)
#1460004
b1101 1
b1000100 5
b10101010 6
b1101 3
b1101 D
b1000100 "
b1000100 H
b10101010 #
b10101010 I
b1101 F
b1101001 2
b1101001 4
b1111 /
b1101001 E
b1101001 G
b1111 B
b11110000 (
b11110000 .
b11110000 A
1)
#1465004
0)
#1470004
b10101010 %
b10101010 =
b1000100 $
b1000100 >
1)
#1475004
0)
#1480004
1)
#1480005
1+
#1485005
0)
#1490005
0+
0!
b0 %
b0 =
b0 $
b0 >
1)
#1495005
0)
#1500005
b0 1
b0 3
b0 D
b0 F
b0 /
b0 B
b0 2
b1 7
b0 4
b100 8
b0 E
b1 J
b0 G
b100 K
b11 9
b110010 5
b110010 6
b10 :
b110010 "
b110010 H
b110010 #
b110010 I
b0 (
b0 .
b0 A
b10100 '
b10100 -
b10100 @
b110010 &
b110010 ,
b110010 ?
1!
b10101010 %
b10101010 =
b1000100 $
b1000100 >
1)
#1505005
0)
#1510005
b110010 %
b110010 =
b110010 $
b110010 >
1)
#1515005
0)
#1520005
b1 2
b100 4
b1 /
b1 E
b100 G
b1 B
b10000 (
b10000 .
b10000 A
1)
#1525005
0)
#1530005
1)
#1535005
0)
#1540005
b1 1
b1001001 5
b101011 6
b111 3
b1 D
b1001001 "
b1001001 H
b101011 #
b101011 I
b111 F
b1111 2
b111100 4
b1111 /
b1111 E
b111100 G
b1111 B
b11110000 (
b11110000 .
b11110000 A
1)
#1545005
0)
#1550005
b101011 %
b101011 =
b1001001 $
b1001001 >
1)
#1555005
0)
#1560005
b1111 1
b100010 5
b1000010 6
b0 3
b1111 D
b100010 "
b100010 H
b1000010 #
b1000010 I
b0 F
b0 /
b11111100 2
b1 4
b1 0
b0 B
b11111100 E
b1 G
b1 C
b1 (
b1 .
b1 A
1)
#1565005
0)
#1570005
b1000010 %
b1000010 =
b100010 $
b100010 >
1)
#1575005
0)
#1580005
b1000 1
b10110011 5
b10110001 6
b1 3
b1000 D
b10110011 "
b10110011 H
b10110001 #
b10110001 I
b1 F
b11000100 2
b1111 4
b1111 0
b11000100 E
b1111 G
b1111 C
b1111 (
b1111 .
b1111 A
1)
#1585005
0)
#1590005
b10110001 %
b10110001 =
b10110011 $
b10110011 >
1)
#1595005
0)
#1600005
b0 3
b0 1
b0 F
b0 D
b0 0
b0 C
b0 4
b10 7
b0 2
b10 8
b0 G
b10 J
b0 E
b10 K
b1 9
b10001 5
b10001 6
b1 :
b10001 "
b10001 H
b10001 #
b10001 I
b0 (
b0 .
b0 A
b100010 '
b100010 -
b100010 @
b10001 &
b10001 ,
b10001 ?
1)
#1605005
0)
#1610005
b10001 %
b10001 =
b10001 $
b10001 >
1)
#1615005
0)
#1620005
b10 2
b10 4
b1 /
b10 E
b10 G
b1 B
b10000 (
b10000 .
b10000 A
1)
#1625005
0)
#1630005
1)
#1635005
0)
#1640005
1)
#1640006
1+
#1645006
0)
#1650006
0+
0!
b0 %
b0 =
b0 $
b0 >
1)
#1655006
0)
#1660006
b1 3
b1111 1
b1 F
b1111 D
b10 /
b1 0
b10 B
b1 C
b11111110 2
b1 7
b1001 4
b100 8
b11111110 E
b1 J
b1001 G
b100 K
b11 9
b100011 5
b1000001 6
b10 :
b100011 "
b100011 H
b1000001 #
b1000001 I
b100001 (
b100001 .
b100001 A
b10100 '
b10100 -
b10100 @
b110010 &
b110010 ,
b110010 ?
1!
b10001 %
b10001 =
b10001 $
b10001 >
1)
#1665006
0)
#1670006
b1000001 %
b1000001 =
b100011 $
b100011 >
1)
#1675006
0)
#1680006
1+
1)
#1685006
0)
#1690006
0!
b0 %
b0 =
b0 $
b0 >
1)
#1695006
0)
#1700006
1)
#1705006
0)
#1710006
1)
#1715006
0)
#1720006
0+
1)
#1725006
0)
#1730006
b0 1
b0 3
b0 D
b0 F
b1 /
b0 0
b1 B
b0 C
b10 7
b10 2
b10 4
b10 8
b10 J
b10 E
b10 G
b10 K
b1 9
b10001 5
b10001 6
b1 :
b10001 "
b10001 H
b10001 #
b10001 I
b10000 (
b10000 .
b10000 A
b100010 '
b100010 -
b100010 @
b10001 &
b10001 ,
b10001 ?
1!
b1000001 %
b1000001 =
b100011 $
b100011 >
1)
#1735006
0)
#1740006
b10001 %
b10001 =
b10001 $
b10001 >
1)
#1745006
0)
#1750006
1)
#1750007
1+
#1755007
0)
#1760007
0+
0!
b0 %
b0 =
b0 $
b0 >
1)
#1765007
0)
#1770007
b1001 1
b1001 D
b1100 3
b1100 F
b1111 /
b1100 0
b1111 B
b1100 C
b1001100 2
b0 7
b11100001 4
b1111 8
b1001100 E
b0 J
b11100001 G
b1111 K
b1011 9
b1000100 5
b101100 6
b1000 :
b1000100 "
b1000100 H
b101100 #
b101100 I
b11111100 (
b11111100 .
b11111100 A
b1111 '
b1111 -
b1111 @
b10111000 &
b10111000 ,
b10111000 ?
1!
b10001 %
b10001 =
b10001 $
b10001 >
1)
#1775007
0)
#1780007
b101100 %
b101100 =
b1000100 $
b1000100 >
1)
#1785007
0)
#1790007
b1111 3
b1111 F
b1000 /
b1010 0
b1000 B
b1010 C
b101 7
b11001110 2
b1111010 4
b1001 8
b101 J
b11001110 E
b1111010 G
b1001 K
b1001001 5
b101011 6
b1010 :
b1001001 "
b1001001 H
b101011 #
b101011 I
b10001010 (
b10001010 .
b10001010 A
b1011001 '
b1011001 -
b1011001 @
b10111010 &
b10111010 ,
b10111010 ?
1)
#1795007
0)
#1800007
b101011 %
b101011 =
b1001001 $
b1001001 >
1)
#1805007
0)
#1810007
b1010 1
b111 3
b1010 D
b111 F
b101 /
b1111 0
b101 B
b1111 C
b1000 7
b1010110 2
b10111110 4
b1110 8
b1000 J
b1010110 E
b10111110 G
b1110 K
b1110 9
b10000110 5
b1001000 6
b1111 :
b10000110 "
b10000110 H
b1001000 #
b1001000 I
b1011111 (
b1011111 .
b1011111 A
b10001110 '
b10001110 -
b10001110 @
b11101111 &
b11101111 ,
b11101111 ?
1)
#1815007
0)
#1820007
b1001000 %
b1001000 =
b10000110 $
b10000110 >
1)
#1825007
0)
#1830007
b1010 3
b1010 F
b1 1
b1 D
b10 0
b10 C
b1110 2
b1010001 4
b1101 8
b1110 E
b1010001 G
b1101 K
b110 9
b1111010 5
b1010110 6
b0 :
b1111010 "
b1111010 H
b1010110 #
b1010110 I
b1010010 (
b1010010 .
b1010010 A
b10001101 '
b10001101 -
b10001101 @
b1100000 &
b1100000 ,
b1100000 ?
1)
#1835007
0)
#1840007
b1010110 %
b1010110 =
b1111010 $
b1111010 >
1)
#1845007
0)
#1850007
b0 1
b100 3
b0 D
b100 F
b1011 /
b1010 0
b1011 B
b1010 C
b1110 7
b10000110 2
b10100010 4
b10 8
b1110 J
b10000110 E
b10100010 G
b10 K
b0 9
b0 5
b1000 6
b1100 :
b0 "
b0 H
b1000 #
b1000 I
b10111010 (
b10111010 .
b10111010 A
b11100010 '
b11100010 -
b11100010 @
b1100 &
b1100 ,
b1100 ?
1)
#1855007
0)
#1860007
b1000 %
b1000 =
b0 $
b0 >
1)
#1865007
0)
#1870007
b1100 1
b11 3
b1100 D
b11 F
b0 /
b1001 0
b0 B
b1001 C
b11 7
b11100101 2
b11011 4
b11 8
b11 J
b11100101 E
b11011 G
b11 K
b100 9
b1110 5
b10001000 6
b1011 :
b1110 "
b1110 H
b10001000 #
b10001000 I
b1001 (
b1001 .
b1001 A
b110011 '
b110011 -
b110011 @
b1001011 &
b1001011 ,
b1001011 ?
1)
#1875007
0)
#1880007
b10001000 %
b10001000 =
b1110 $
b1110 >
1)
#1885007
0)
#1890007
b10 3
b10 F
b1 /
b11 0
b1 B
b11 C
b10110 4
b100 7
b11100110 2
b1010 8
b10110 G
b100 J
b11100110 E
b1010 K
b101101 5
b10101001 6
b110 9
b101101 "
b101101 H
b10101001 #
b10101001 I
b10011 (
b10011 .
b10011 A
b1001010 '
b1001010 -
b1001010 @
b1101011 &
b1101011 ,
b1101011 ?
1)
#1895007
0)
#1900007
b10101001 %
b10101001 =
b101101 $
b101101 >
1)
#1905007
0)
#1910007
b1110 1
b1101 3
b1110 D
b1101 F
b1010 0
b1010 C
b1001 7
b1110011 2
b1101001 4
b1111 8
b1001 J
b1110011 E
b1101001 G
b1111 K
b1110 9
b11000111 5
b1101 6
b1010 :
b11000111 "
b11000111 H
b1101 #
b1101 I
b11010 (
b11010 .
b11010 A
b10011111 '
b10011111 -
b10011111 @
b11101010 &
b11101010 ,
b11101010 ?
1)
#1915007
0)
#1920007
b1101 %
b1101 =
b11000111 $
b11000111 >
1)
#1925007
0)
#1930007
b11 1
b1 3
b11 D
b1 F
b110 /
b11 0
b110 B
b11 C
b100 7
b11000 2
b1100 4
b0 8
b100 J
b11000 E
b1100 G
b0 K
b1111 9
b101100 5
b11001010 6
b1011 :
b101100 "
b101100 H
b11001010 #
b11001010 I
b1100011 (
b1100011 .
b1100011 A
b1000000 '
b1000000 -
b1000000 @
b11111011 &
b11111011 ,
b11111011 ?
1)
#1935007
0)
#1940007
b11001010 %
b11001010 =
b101100 $
b101100 >
1)
#1945007
0)
#1950007
b1110 1
b11 3
b1110 D
b11 F
b0 /
b1010 0
b0 B
b1010 C
b11 7
b1110100 2
b11110 4
b1110 8
b11 J
b1110100 E
b11110 G
b1110 K
b1101 9
b10110110 5
b11110000 6
b11 :
b10110110 "
b10110110 H
b11110000 #
b11110000 I
b1010 (
b1010 .
b1010 A
b111110 '
b111110 -
b111110 @
b11010011 &
b11010011 ,
b11010011 ?
1)
#1955007
0)
#1960007
b11110000 %
b11110000 =
b10110110 $
b10110110 >
1)
#1965007
0)
#1970007
b110 1
b110 D
b100 /
b0 0
b100 B
b0 C
b11000 4
b1101 7
b110100 2
b110 8
b11000 G
b1101 J
b110100 E
b110 K
b110010 5
b1111100 6
b1111 :
b110010 "
b110010 H
b1111100 #
b1111100 I
b1000000 (
b1000000 .
b1000000 A
b11010110 '
b11010110 -
b11010110 @
b11011111 &
b11011111 ,
b11011111 ?
1)
#1975007
0)
#1980007
b1111100 %
b1111100 =
b110010 $
b110010 >
1)
#1985007
0)
#1990007
b1001 /
b10 0
b1001 B
b10 C
b110011 2
b1001 7
b10011001 4
b1111 8
b110011 E
b1001 J
b10011001 G
b1111 K
b1111 9
b1010101 5
b10011111 6
b10 :
b1010101 "
b1010101 H
b10011111 #
b10011111 I
b10010010 (
b10010010 .
b10010010 A
b10011111 '
b10011111 -
b10011111 @
b11110010 &
b11110010 ,
b11110010 ?
1)
#1995007
0)
#2000007
b10011111 %
b10011111 =
b1010101 $
b1010101 >
1)
#2005007
0)
#2010007
b1010 1
b101 3
b1010 D
b101 F
b10 /
b1110 0
b10 B
b1110 C
b1010 7
b1010000 2
b10101000 4
b1110 8
b1010 J
b1010000 E
b10101000 G
b1110 K
b100 9
b11100101 5
b10101011 6
b0 :
b11100101 "
b11100101 H
b10101011 #
b10101011 I
b101110 (
b101110 .
b101110 A
b10101110 '
b10101110 -
b10101110 @
b1000000 &
b1000000 ,
b1000000 ?
1)
#2015007
0)
#2020007
b10101011 %
b10101011 =
b11100101 $
b11100101 >
1)
#2025007
0)
#2030007
b1110 1
b1001 3
b1110 D
b1001 F
b0 /
b1100 0
b0 B
b1100 C
b110 7
b1110000 2
b1001000 4
b1100 8
b110 J
b1110000 E
b1001000 G
b1100 K
b111 9
b1011101 5
b10011011 6
b100 :
b1011101 "
b1011101 H
b10011011 #
b10011011 I
b1100 (
b1100 .
b1100 A
b1101100 '
b1101100 -
b1101100 @
b1110100 &
b1110100 ,
b1110100 ?
1)
#2035007
0)
#2040007
b10011011 %
b10011011 =
b1011101 $
b1011101 >
1)
#2045007
0)
#2050007
b1010 3
b1010 1
b1010 F
b1010 D
b11 /
b1111 0
b11 B
b1111 C
b1010111 4
b101 7
b11010011 2
b100 8
b1010111 G
b101 J
b11010011 E
b100 K
b1111 9
b10011010 5
b1010110 6
b0 :
b10011010 "
b10011010 H
b1010110 #
b1010110 I
b111111 (
b111111 .
b111111 A
b1010100 '
b1010100 -
b1010100 @
b11110000 &
b11110000 ,
b11110000 ?
1)
#2055007
0)
#2060007
b1010110 %
b1010110 =
b10011010 $
b10011010 >
1)
#2065007
0)
#2070007
b0 1
b1011 3
b0 D
b1011 F
b1011 /
b1100 0
b1011 B
b1100 C
b1010 7
b10 2
b11011011 4
b1001 8
b1010 J
b10 E
b11011011 G
b1001 K
b1100 9
b11000010 5
b11001100 6
b111 :
b11000010 "
b11000010 H
b11001100 #
b11001100 I
b10111100 (
b10111100 .
b10111100 A
b10101001 '
b10101001 -
b10101001 @
b11000111 &
b11000111 ,
b11000111 ?
1)
#2075007
0)
#2080007
b11001100 %
b11001100 =
b11000010 $
b11000010 >
1)
#2085007
0)
