src/butterfly.sv
module butterfly #(
    parameter WIDTH = 8
)(
    input  logic signed [WIDTH-1:0] A_real, A_imag,
    input  logic signed [WIDTH-1:0] B_real, B_imag,
    input  logic signed [WIDTH-1:0] W_real, W_imag,
    output logic signed [WIDTH-1:0] Pos_real, Pos_imag,
    output logic signed [WIDTH-1:0] Neg_real, Neg_imag
);
    // Complex multiplication: W * B
    logic signed [15:0] product_real, product_imag;
    
    assign product_real = (W_real * B_real) - (W_imag * B_imag);
    assign product_imag = (W_real * B_imag) + (W_imag * B_real);
    
    // Scale and add/subtract
    assign Pos_real = A_real + (product_real >>> (WIDTH-1));
    assign Pos_imag = A_imag + (product_imag >>> (WIDTH-1));
    assign Neg_real = A_real - (product_real >>> (WIDTH-1));
    assign Neg_imag = A_imag - (product_imag >>> (WIDTH-1));
endmodule

test/butterfly_unit/butterfly_tb.sv
`default_nettype none
`timescale 1ns / 1ps

module butterfly_tb (
    input  logic signed [7:0] A_real, A_imag,
    input  logic signed [7:0] B_real, B_imag,
    input  logic signed [7:0] W_real, W_imag,
    output logic signed [7:0] Pos_real, Pos_imag,
    output logic signed [7:0] Neg_real, Neg_imag
);

    // Dump the signals to a VCD file
    string vcd_name;
    initial begin
`ifdef VCD_PATH
        vcd_name = `VCD_PATH;
`else
        vcd_name = {"butterfly_tb_", `TIMESTAMP, ".vcd"};
`endif
        $dumpfile(vcd_name);
        $dumpvars(0, butterfly_tb);
        #1;
    end

    // Instantiate the butterfly unit (DUT)
    butterfly dut (
        .A_real(A_real),
        .A_imag(A_imag),
        .B_real(B_real),
        .B_imag(B_imag),
        .W_real(W_real),
        .W_imag(W_imag),
        .Pos_real(Pos_real),
        .Pos_imag(Pos_imag),
        .Neg_real(Neg_real),
        .Neg_imag(Neg_imag)
    );

endmodule

test/butterfly_unit/wave/butterfly_tb_20250707_20:12:56.vcd
$date
	Mon Jul  7 20:13:02 2025
$end
$version
	Icarus Verilog
$end
$timescale
	1ps
$end
$scope module butterfly_tb $end
$var wire 8 ! A_imag [7:0] $end
$var wire 8 " A_real [7:0] $end
$var wire 8 # B_imag [7:0] $end
$var wire 8 $ B_real [7:0] $end
$var wire 8 % W_imag [7:0] $end
$var wire 8 & W_real [7:0] $end
$var wire 8 ' Pos_real [7:0] $end
$var wire 8 ( Pos_imag [7:0] $end
$var wire 8 ) Neg_real [7:0] $end
$var wire 8 * Neg_imag [7:0] $end
$scope module dut $end
$var wire 8 + A_imag [7:0] $end
$var wire 8 , A_real [7:0] $end
$var wire 8 - B_imag [7:0] $end
$var wire 8 . B_real [7:0] $end
$var wire 8 / W_imag [7:0] $end
$var wire 8 0 W_real [7:0] $end
$var wire 16 1 product_real [15:0] $end
$var wire 16 2 product_imag [15:0] $end
$var wire 8 3 Pos_real [7:0] $end
$var wire 8 4 Pos_imag [7:0] $end
$var wire 8 5 Neg_real [7:0] $end
$var wire 8 6 Neg_imag [7:0] $end
$upscope $end
$upscope $end
$enddefinitions $end
#0
$dumpvars
b10101 6
b1011 5
b10011 4
b1001 3
b1111111111110001 2
b1111111111111011 1
b11111111 0
b0 /
b101 .
b1111 -
b1010 ,
b10100 +
b10101 *
b1011 )
b10011 (
b1001 '
b11111111 &
b0 %
b101 $
b1111 #
b1010 "
b10100 !
$end
#1001
b1010 '
b1010 3
b1010 )
b1010 5
b11111111 %
b11111111 /
b1111 1
b1111111111111011 2
b0 &
b0 0
#2002
b0 (
b0 4
b10 *
b10 6
b0 '
b0 3
b10 )
b10 5
b0 %
b0 /
b11111111 &
b11111111 0
b1111111111111110 1
b10 #
b10 -
b1111111111111110 2
b10 $
b10 .
b1 !
b1 +
b1 "
b1 ,
#3003
b11111111 (
b11111111 4
b1 *
b1 6
b0 '
b0 3
b0 )
b0 5
b11111111 %
b11111111 /
b0 1
b0 &
b0 0
b1111111111111110 2
b0 #
b0 -
b0 !
b0 +
b0 "
b0 ,
#4004
b1000110 (
b1000110 4
b1000110 *
b1000110 6
b11100 '
b11100 3
b11110 )
b11110 5
b0 %
b0 /
b11111111 &
b11111111 0
b1111111111001110 1
b10000011 #
b10000011 -
b1111101 2
b110010 $
b110010 .
b1000110 !
b1000110 +
b11101 "
b11101 ,
#5004
b101100 (
b101100 4
b101100 *
b101100 6
b1011100 '
b1011100 3
b1011110 )
b1011110 5
b11111111 %
b11111111 /
b0 &
b0 0
b110100 2
b10011100 #
b10011100 -
b1111111110011100 1
b11001100 $
b11001100 .
b101100 !
b101100 +
b1011101 "
b1011101 ,
#6004
b1111111 (
b1111111 4
b1111111 *
b1111111 6
b11000000 '
b11000000 3
b11000000 )
b11000000 5
b0 %
b0 /
b11111111 &
b11111111 0
b1000000 1
b11000000 #
b11000000 -
b1000000 2
b11000000 $
b11000000 .
b1111111 !
b1111111 +
b11000000 "
b11000000 ,
#7004
b10011011 (
b10011011 4
b10011101 *
b10011101 6
b1100100 '
b1100100 3
b1100100 )
b1100100 5
b11111111 %
b11111111 /
b0 &
b0 0
b1111111111110110 2
b1010 #
b1010 -
b1010 1
b1010 $
b1010 .
b10011100 !
b10011100 +
b1100100 "
b1100100 ,
