src/display_ctrl.sv
module display_ctrl (
    input  logic [1:0] sample_counter,
    input  logic [1:0] output_counter,
    input  logic processing, done,
    output logic [7:0] seg_out
);
    // 7-segment encodings
    localparam [7:0] 
        D_1 = 8'b00001100, D_2 = 8'b01011010,
        D_3 = 8'b01001110, D_4 = 8'b01100100,
        D_C = 8'b00111000, D_5 = 8'b01101100,
        D_6 = 8'b01111100, D_7 = 8'b00001110;
    
    always_comb begin
        if (processing) seg_out = D_C;
        else if (done) begin
            case(output_counter + 1)
                2'd1: seg_out = D_5;
                2'd2: seg_out = D_6;
                2'd3: seg_out = D_7;
                default: seg_out = D_5;
            endcase
        end else begin
            case(sample_counter + 1)
                2'd1: seg_out = D_1;
                2'd2: seg_out = D_2;
                2'd3: seg_out = D_3;
                2'd4: seg_out = D_4;
                default: seg_out = 8'b0;
            endcase
        end
    end
endmodule

src/butterfly.sv
module butterfly #(
    parameter WIDTH = 8
)(
    input  logic signed [WIDTH-1:0] A_real, A_imag,
    input  logic signed [WIDTH-1:0] B_real, B_imag,
    input  logic signed [WIDTH-1:0] W_real, W_imag,
    output logic signed [WIDTH-1:0] Pos_real, Pos_imag,
    output logic signed [WIDTH-1:0] Neg_real, Neg_imag
);
    // Complex multiplication: W * B
    logic signed [15:0] product_real, product_imag;
    
    assign product_real = (W_real * B_real) - (W_imag * B_imag);
    assign product_imag = (W_real * B_imag) + (W_imag * B_real);
    
    // Scale and add/subtract
    assign Pos_real = A_real + (product_real >>> (WIDTH-1));
    assign Pos_imag = A_imag + (product_imag >>> (WIDTH-1));
    assign Neg_real = A_real - (product_real >>> (WIDTH-1));
    assign Neg_imag = A_imag - (product_imag >>> (WIDTH-1));
endmodule

src/fft_engine.sv
module fft_engine #(
    parameter WIDTH = 8
)(
    input  logic clk, rst,
    // Individual input ports
    input  logic signed [WIDTH-1:0] in0_real, in0_imag,
    input  logic signed [WIDTH-1:0] in1_real, in1_imag,
    input  logic signed [WIDTH-1:0] in2_real, in2_imag,
    input  logic signed [WIDTH-1:0] in3_real, in3_imag,
    // Individual output ports
    output logic signed [WIDTH-1:0] out0_real, out0_imag,
    output logic signed [WIDTH-1:0] out1_real, out1_imag,
    output logic signed [WIDTH-1:0] out2_real, out2_imag,
    output logic signed [WIDTH-1:0] out3_real, out3_imag
);
    // Twiddle factors
    localparam logic signed [WIDTH-1:0] W0_real = 8'sh80; // 1.0
    localparam logic signed [WIDTH-1:0] W0_imag = 8'sh00;
    localparam logic signed [WIDTH-1:0] W1_real = 8'sh00;  // -j
    localparam logic signed [WIDTH-1:0] W1_imag = 8'sh80;
    
    // Stage 1 results
    logic signed [WIDTH-1:0] s1_real[0:3];
    logic signed [WIDTH-1:0] s1_imag[0:3];
    
    // Instantiate butterfly units for stage 1
    butterfly bfly_stage1_0 (
        .A_real(in0_real), .A_imag(in0_imag),
        .B_real(in2_real), .B_imag(in2_imag),
        .W_real(W0_real), .W_imag(W0_imag),
        .Pos_real(s1_real[0]), .Pos_imag(s1_imag[0]),
        .Neg_real(s1_real[1]), .Neg_imag(s1_imag[1])
    );
    
    butterfly bfly_stage1_1 (
        .A_real(in1_real), .A_imag(in1_imag),
        .B_real(in3_real), .B_imag(in3_imag),
        .W_real(W0_real), .W_imag(W0_imag),
        .Pos_real(s1_real[2]), .Pos_imag(s1_imag[2]),
        .Neg_real(s1_real[3]), .Neg_imag(s1_imag[3])
    );
    
    // Stage 2 processing
    always_ff @(posedge clk or posedge rst) begin
        if (rst) begin
            out0_real <= '0; out0_imag <= '0;
            out1_real <= '0; out1_imag <= '0;
            out2_real <= '0; out2_imag <= '0;
            out3_real <= '0; out3_imag <= '0;
        end else begin
            // First butterfly (no multiplication needed)
            out0_real <= s1_real[0] + s1_real[2];
            out0_imag <= s1_imag[0] + s1_imag[2];
            out2_real <= s1_real[0] - s1_real[2];
            out2_imag <= s1_imag[0] - s1_imag[2];
            
            // Second butterfly (with twiddle factor)
            // Create temporary variables for butterfly outputs
            logic signed [WIDTH-1:0] bfly_pos_real, bfly_pos_imag;
            logic signed [WIDTH-1:0] bfly_neg_real, bfly_neg_imag;
            
            butterfly bfly_stage2_1 (
                .A_real(s1_real[1]), .A_imag(s1_imag[1]),
                .B_real(s1_real[3]), .B_imag(s1_imag[3]),
                .W_real(W1_real), .W_imag(W1_imag),
                .Pos_real(bfly_pos_real), .Pos_imag(bfly_pos_imag),
                .Neg_real(bfly_neg_real), .Neg_imag(bfly_neg_imag)
            );
            
            out1_real <= bfly_pos_real;
            out1_imag <= bfly_pos_imag;
            out3_real <= bfly_neg_real;
            out3_imag <= bfly_neg_imag;
        end
    end
endmodule

src/memory_ctrl.sv
module memory_ctrl #(
    parameter WIDTH = 8
)(
    input  logic clk, rst, ena,
    input  logic load_pulse,
    input  logic [1:0] addr,
    input  logic [7:0] data_in,
    output logic signed [WIDTH-1:0] real0_out, imag0_out,
    output logic signed [WIDTH-1:0] real1_out, imag1_out,
    output logic signed [WIDTH-1:0] real2_out, imag2_out,
    output logic signed [WIDTH-1:0] real3_out, imag3_out
);
    // Sample storage
    logic signed [WIDTH-1:0] real_mem[0:3];
    logic signed [WIDTH-1:0] imag_mem[0:3];
    
    // Initialize arrays properly
    integer i;
    always_ff @(posedge clk or posedge rst) begin
        if (rst) begin
            for (i = 0; i < 4; i = i + 1) begin
                real_mem[i] <= 0;
                imag_mem[i] <= 0;
            end
        end else if (ena && load_pulse) begin
            real_mem[addr] <= $signed(data_in[7:4]) << 4;
            imag_mem[addr] <= $signed(data_in[3:0]) << 4;
        end
    end
    
    // Continuous assignments for outputs
    assign real0_out = real_mem[0];
    assign imag0_out = imag_mem[0];
    assign real1_out = real_mem[1];
    assign imag1_out = imag_mem[1];
    assign real2_out = real_mem[2];
    assign imag2_out = imag_mem[2];
    assign real3_out = real_mem[3];
    assign imag3_out = imag_mem[3];
endmodule

src/io_ctrl.sv
module io_ctrl (
    input  logic clk, rst, ena,
    input  logic ui_in0, ui_in1,
    output logic load_pulse,
    output logic output_pulse,
    output logic [1:0] addr
);
    logic [1:0] counter;
    logic prev_in0, prev_in1;
    
    always_ff @(posedge clk or posedge rst) begin
        if (rst) begin
            counter <= '0;
            prev_in0 <= '0;
            prev_in1 <= '0;
        end else if (ena) begin
            prev_in0 <= ui_in0;
            prev_in1 <= ui_in1;
            
            if (ui_in0 && !prev_in0) begin
                counter <= counter + 1;
            end
        end
    end
    
    assign load_pulse = ui_in0 && !prev_in0;
    assign output_pulse = ui_in1 && !prev_in1;
    assign addr = counter;
endmodule

src/top_fft.sv
module tt_um_FFT_engine (
    input  wire [7:0] ui_in,
    output logic [7:0] uo_out,
    input  wire [7:0] uio_in,
    output logic [7:0] uio_out,
    output logic [7:0] uio_oe,
    input  wire       ena,
    input  wire       clk,
    input  wire       rst_n
);
    // System signals
    wire rst = ~rst_n;
    
    // Control signals
    wire load_pulse, output_pulse;
    wire [1:0] addr;
    
    // Individual sample storage
    logic signed [7:0] sample0_real, sample0_imag;
    logic signed [7:0] sample1_real, sample1_imag;
    logic signed [7:0] sample2_real, sample2_imag;
    logic signed [7:0] sample3_real, sample3_imag;
    
    // Individual FFT outputs
    logic signed [7:0] fft0_real, fft0_imag;
    logic signed [7:0] fft1_real, fft1_imag;
    logic signed [7:0] fft2_real, fft2_imag;
    logic signed [7:0] fft3_real, fft3_imag;
    
    // State tracking
    logic processing, done;
    logic processing_dly;
    logic [1:0] output_counter;
    
    // Module instantiations
    io_ctrl io_inst (
        .clk(clk), .rst(rst), .ena(ena),
        .ui_in0(ui_in[0]), .ui_in1(ui_in[1]),
        .load_pulse(load_pulse),
        .output_pulse(output_pulse),
        .addr(addr)
    );
    
    memory_ctrl mem_inst (
        .clk(clk), .rst(rst), .ena(ena),
        .load_pulse(load_pulse),
        .addr(addr),
        .data_in(uio_in),
        .real0_out(sample0_real), .imag0_out(sample0_imag),
        .real1_out(sample1_real), .imag1_out(sample1_imag),
        .real2_out(sample2_real), .imag2_out(sample2_imag),
        .real3_out(sample3_real), .imag3_out(sample3_imag)
    );
    
    // Connect FFT engine using individual signals
    fft_engine fft_inst (
        .clk(clk), .rst(rst),
        .in0_real(sample0_real), .in0_imag(sample0_imag),
        .in1_real(sample1_real), .in1_imag(sample1_imag),
        .in2_real(sample2_real), .in2_imag(sample2_imag),
        .in3_real(sample3_real), .in3_imag(sample3_imag),
        .out0_real(fft0_real), .out0_imag(fft0_imag),
        .out1_real(fft1_real), .out1_imag(fft1_imag),
        .out2_real(fft2_real), .out2_imag(fft2_imag),
        .out3_real(fft3_real), .out3_imag(fft3_imag)
    );
    
    display_ctrl disp_inst (
        .sample_counter(addr),
        .output_counter(output_counter),
        .processing(processing), .done(done),
        .seg_out(uo_out)
    );
    
    // Output control
    always_ff @(posedge clk or posedge rst) begin
        if (rst) begin
            processing <= '0;
            done <= '0;
            output_counter <= '0;
            uio_oe <= '0;
            processing_dly <= '0;
        end else if (ena) begin
            processing_dly <= processing;
            if (load_pulse && addr == 2'd3) 
                processing <= '1;
            else if (processing) 
                processing <= '0;
            
            if (processing_dly && !processing)
                done <= '1;
            else if (output_pulse && output_counter == 2'd3)
                done <= '0;
            
            if (output_pulse && done) begin
                uio_oe <= '1;
                output_counter <= (output_counter == 2'd3) ? '0 : output_counter + 1;
            end else begin
                uio_oe <= '0;
            end
        end
    end
    
    // Output selection using a case statement
    always_comb begin
        case(output_counter)
            2'd0: uio_out = {fft0_real[7:4], fft0_imag[7:4]};
            2'd1: uio_out = {fft1_real[7:4], fft1_imag[7:4]};
            2'd2: uio_out = {fft2_real[7:4], fft2_imag[7:4]};
            2'd3: uio_out = {fft3_real[7:4], fft3_imag[7:4]};
            default: uio_out = 8'h00;
        endcase
    end
endmodule

test/top_fft/top_fft_tb.sv
`default_nettype none
`timescale 1ns / 1ps

module tt_um_FFT_engine_tb (
    // To DUT
    input  wire [7:0] ui_in,
    input  wire [7:0] uio_in,
    input  wire       ena,
    input  wire       clk,
    input  wire       rst_n,

    // From DUT
    output wire [7:0] uo_out,
    output wire [7:0] uio_out,
    output wire [7:0] uio_oe
);

logic [7:0] current_test_id = 0;

    // Dump signals for waveform viewing
    string vcd_name;
    initial begin
`ifdef VCD_PATH
        vcd_name = `VCD_PATH;
`else
        vcd_name = {"tt_um_FFT_engine_tb_", `TIMESTAMP, ".vcd"};
`endif
        $dumpfile(vcd_name);
        $dumpvars(0, tt_um_FFT_engine_tb);
        #1;
    end

    // Instantiate the top-level DUT
    tt_um_FFT_engine dut (
        .ui_in(ui_in),
        .uo_out(uo_out),
        .uio_in(uio_in),
        .uio_out(uio_out),
        .uio_oe(uio_oe),
        .ena(ena),
        .clk(clk),
        .rst_n(rst_n)
    );

endmodule

test/top_fft/wave/tt_um_FFT_engine_tb_20250707_22:36:01.vcd
$date
	Mon Jul  7 22:36:04 2025
$end
$version
	Icarus Verilog
$end
$timescale
	1ps
$end
$scope module tt_um_FFT_engine_tb $end
$var wire 1 ! clk $end
$var wire 1 " ena $end
$var wire 1 # rst_n $end
$var wire 8 $ ui_in [7:0] $end
$var wire 8 % uio_in [7:0] $end
$var wire 8 & uo_out [7:0] $end
$var wire 8 ' uio_out [7:0] $end
$var wire 8 ( uio_oe [7:0] $end
$var reg 8 ) current_test_id [7:0] $end
$scope module dut $end
$var wire 1 ! clk $end
$var wire 1 " ena $end
$var wire 1 * rst $end
$var wire 1 # rst_n $end
$var wire 8 + sample0_imag [7:0] $end
$var wire 8 , sample0_real [7:0] $end
$var wire 8 - sample1_imag [7:0] $end
$var wire 8 . sample1_real [7:0] $end
$var wire 8 / sample2_imag [7:0] $end
$var wire 8 0 sample2_real [7:0] $end
$var wire 8 1 sample3_imag [7:0] $end
$var wire 8 2 sample3_real [7:0] $end
$var wire 8 3 ui_in [7:0] $end
$var wire 8 4 uio_in [7:0] $end
$var wire 8 5 uo_out [7:0] $end
$var wire 8 6 uio_oe [7:0] $end
$var wire 1 7 output_pulse $end
$var wire 1 8 load_pulse $end
$var wire 8 9 fft3_real [7:0] $end
$var wire 8 : fft3_imag [7:0] $end
$var wire 8 ; fft2_real [7:0] $end
$var wire 8 < fft2_imag [7:0] $end
$var wire 8 = fft1_real [7:0] $end
$var wire 8 > fft1_imag [7:0] $end
$var wire 8 ? fft0_real [7:0] $end
$var wire 8 @ fft0_imag [7:0] $end
$var wire 2 A addr [1:0] $end
$var reg 1 B done $end
$var reg 2 C output_counter [1:0] $end
$var reg 1 D processing $end
$var reg 1 E processing_dly $end
$var reg 8 F uio_out [7:0] $end
$scope module disp_inst $end
$var wire 1 B done $end
$var wire 2 G output_counter [1:0] $end
$var wire 1 D processing $end
$var wire 2 H sample_counter [1:0] $end
$var parameter 8 I D_1 $end
$var parameter 8 J D_2 $end
$var parameter 8 K D_3 $end
$var parameter 8 L D_4 $end
$var parameter 8 M D_5 $end
$var parameter 8 N D_6 $end
$var parameter 8 O D_7 $end
$var parameter 8 P D_C $end
$var reg 8 Q seg_out [7:0] $end
$upscope $end
$scope module fft_inst $end
$var wire 1 ! clk $end
$var wire 8 R in0_imag [7:0] $end
$var wire 8 S in0_real [7:0] $end
$var wire 8 T in1_imag [7:0] $end
$var wire 8 U in1_real [7:0] $end
$var wire 8 V in2_imag [7:0] $end
$var wire 8 W in2_real [7:0] $end
$var wire 8 X in3_imag [7:0] $end
$var wire 8 Y in3_real [7:0] $end
$var wire 1 * rst $end
$var wire 8 Z bfly_pos_real [7:0] $end
$var wire 8 [ bfly_pos_imag [7:0] $end
$var wire 8 \ bfly_neg_real [7:0] $end
$var wire 8 ] bfly_neg_imag [7:0] $end
$var parameter 8 ^ W0_imag $end
$var parameter 8 _ W0_real $end
$var parameter 8 ` W1_imag $end
$var parameter 8 a W1_real $end
$var parameter 32 b WIDTH $end
$var reg 8 c out0_imag [7:0] $end
$var reg 8 d out0_real [7:0] $end
$var reg 8 e out1_imag [7:0] $end
$var reg 8 f out1_real [7:0] $end
$var reg 8 g out2_imag [7:0] $end
$var reg 8 h out2_real [7:0] $end
$var reg 8 i out3_imag [7:0] $end
$var reg 8 j out3_real [7:0] $end
$scope module bfly_stage1_0 $end
$var wire 8 k A_imag [7:0] $end
$var wire 8 l A_real [7:0] $end
$var wire 8 m B_imag [7:0] $end
$var wire 8 n B_real [7:0] $end
$var wire 8 o W_imag [7:0] $end
$var wire 8 p W_real [7:0] $end
$var wire 16 q product_real [15:0] $end
$var wire 16 r product_imag [15:0] $end
$var wire 8 s Pos_real [7:0] $end
$var wire 8 t Pos_imag [7:0] $end
$var wire 8 u Neg_real [7:0] $end
$var wire 8 v Neg_imag [7:0] $end
$var parameter 32 w WIDTH $end
$upscope $end
$scope module bfly_stage1_1 $end
$var wire 8 x A_imag [7:0] $end
$var wire 8 y A_real [7:0] $end
$var wire 8 z B_imag [7:0] $end
$var wire 8 { B_real [7:0] $end
$var wire 8 | W_imag [7:0] $end
$var wire 8 } W_real [7:0] $end
$var wire 16 ~ product_real [15:0] $end
$var wire 16 !" product_imag [15:0] $end
$var wire 8 "" Pos_real [7:0] $end
$var wire 8 #" Pos_imag [7:0] $end
$var wire 8 $" Neg_real [7:0] $end
$var wire 8 %" Neg_imag [7:0] $end
$var parameter 32 &" WIDTH $end
$upscope $end
$scope module bfly_stage2_1 $end
$var wire 8 '" A_imag [7:0] $end
$var wire 8 (" A_real [7:0] $end
$var wire 8 )" B_imag [7:0] $end
$var wire 8 *" B_real [7:0] $end
$var wire 8 +" W_imag [7:0] $end
$var wire 8 ," W_real [7:0] $end
$var wire 16 -" product_real [15:0] $end
$var wire 16 ." product_imag [15:0] $end
$var wire 8 /" Pos_real [7:0] $end
$var wire 8 0" Pos_imag [7:0] $end
$var wire 8 1" Neg_real [7:0] $end
$var wire 8 2" Neg_imag [7:0] $end
$var parameter 32 3" WIDTH $end
$upscope $end
$upscope $end
$scope module io_inst $end
$var wire 2 4" addr [1:0] $end
$var wire 1 ! clk $end
$var wire 1 " ena $end
$var wire 1 8 load_pulse $end
$var wire 1 7 output_pulse $end
$var wire 1 * rst $end
$var wire 1 5" ui_in0 $end
$var wire 1 6" ui_in1 $end
$var reg 2 7" counter [1:0] $end
$var reg 1 8" prev_in0 $end
$var reg 1 9" prev_in1 $end
$upscope $end
$scope module mem_inst $end
$var wire 2 :" addr [1:0] $end
$var wire 1 ! clk $end
$var wire 8 ;" data_in [7:0] $end
$var wire 1 " ena $end
$var wire 8 <" imag0_out [7:0] $end
$var wire 8 =" imag1_out [7:0] $end
$var wire 8 >" imag2_out [7:0] $end
$var wire 8 ?" imag3_out [7:0] $end
$var wire 1 8 load_pulse $end
$var wire 8 @" real0_out [7:0] $end
$var wire 8 A" real1_out [7:0] $end
$var wire 8 B" real2_out [7:0] $end
$var wire 8 C" real3_out [7:0] $end
$var wire 1 * rst $end
$var parameter 32 D" WIDTH $end
$var integer 32 E" i [31:0] $end
$upscope $end
$upscope $end
$upscope $end
$enddefinitions $end
$comment Show the parameter values. $end
$dumpall
b1000 D"
b1000 3"
b1000 &"
b1000 w
b1000 b
b0 a
b10000000 `
b10000000 _
b0 ^
b111000 P
b1110 O
b1111100 N
b1101100 M
b1100100 L
b1001110 K
b1011010 J
b1100 I
$end
#0
$dumpvars
b100 E"
b0 C"
b0 B"
b0 A"
b0 @"
b0 ?"
b0 >"
b0 ="
b0 <"
b0 ;"
b0 :"
09"
08"
b0 7"
06"
05"
b0 4"
b0 2"
b0 1"
b0 0"
b0 /"
b0 ."
b0 -"
b0 ,"
b10000000 +"
b0 *"
b0 )"
b0 ("
b0 '"
b0 %"
b0 $"
b0 #"
b0 ""
b0 !"
b0 ~
b10000000 }
b0 |
b0 {
b0 z
b0 y
b0 x
b0 v
b0 u
b0 t
b0 s
b0 r
b0 q
b10000000 p
b0 o
b0 n
b0 m
b0 l
b0 k
b0 j
b0 i
b0 h
b0 g
b0 f
b0 e
b0 d
b0 c
b0 ]
b0 \
b0 [
b0 Z
b0 Y
b0 X
b0 W
b0 V
b0 U
b0 T
b0 S
b0 R
b1100 Q
b0 H
b0 G
b0 F
0E
0D
b0 C
0B
b0 A
b0 @
b0 ?
b0 >
b0 =
b0 <
b0 ;
b0 :
b0 9
08
07
b0 6
b1100 5
b0 4
b0 3
b0 2
b0 1
b0 0
b0 /
b0 .
b0 -
b0 ,
b0 +
1*
b1 )
b0 (
b0 '
b1100 &
b0 %
b0 $
0#
0"
1!
$end
#5000
0!
#10000
0*
1#
b100 E"
1!
#15000
0!
#20000
1!
#20001
b100 E"
1*
0#
b10 )
#25001
0!
#30001
b100 E"
1!
#35001
0!
#40001
0*
1#
b100 E"
1!
#45001
0!
#50001
18
15"
b1 $
b1 3
b10010 %
b10010 4
b10010 ;"
1"
1!
#55001
0!
#60001
05"
b0 $
b0 3
b100000 [
b100000 0"
b100000 ]
b100000 2"
b10000 Z
b10000 /"
b10000 \
b10000 1"
b100000 t
b100000 v
b100000 '"
b10000 s
b10000 u
b10000 ("
b1011010 &
b1011010 5
b1011010 Q
08
b100000 +
b100000 R
b100000 k
b100000 <"
b10000 ,
b10000 S
b10000 l
b10000 @"
b1 A
b1 H
b1 4"
b1 :"
b1 7"
18"
1!
#65001
0!
#70001
18
15"
b1 $
b1 3
b11011100 %
b11011100 4
b11011100 ;"
b10010 '
b10010 F
08"
b100000 :
b100000 i
b10000 9
b10000 j
b100000 >
b100000 e
b10000 =
b10000 f
b100000 <
b100000 g
b10000 ;
b10000 h
b100000 @
b100000 c
b10000 ?
b10000 d
1!
#75001
0!
#80001
05"
b0 $
b0 3
b11010000 Z
b11010000 /"
b1010000 \
b1010000 1"
b1010000 [
b1010000 0"
b11110000 ]
b11110000 2"
b11000000 #"
b1110000000000000 -"
b11000000 %"
b11000000 )"
b11010000 ""
b1100000000000 ."
b11010000 $"
b11010000 *"
b1001110 &
b1001110 5
b1001110 Q
08
b11000000 -
b11000000 T
b11000000 x
b11000000 ="
b11010000 .
b11010000 U
b11010000 y
b11010000 A"
b10 A
b10 H
b10 4"
b10 :"
b10 7"
18"
1!
#85001
0!
#90001
18
15"
b1 $
b1 3
b1011010 %
b1011010 4
b1011010 ;"
b11101110 '
b11101110 F
08"
b11110000 :
b11110000 i
b1010000 9
b1010000 j
b1010000 >
b1010000 e
b11010000 =
b11010000 f
b1100000 <
b1100000 g
b1000000 ;
b1000000 h
b11100000 @
b11100000 c
b11100000 ?
b11100000 d
1!
#95001
0!
#100001
05"
b0 $
b0 3
b11110000 [
b11110000 0"
b10010000 ]
b10010000 2"
b100000 Z
b100000 /"
b10100000 \
b10100000 1"
b10000000 t
b11000000 v
b11000000 '"
b11000000 s
b1100000 u
b1100000 ("
b0 &
b0 5
b0 Q
08
b11000000000000 r
b10100000 /
b10100000 V
b10100000 m
b10100000 >"
b1101100000000000 q
b1010000 0
b1010000 W
b1010000 n
b1010000 B"
b11 A
b11 H
b11 4"
b11 :"
b11 7"
18"
1!
#105001
0!
#110001
18
15"
b1 $
b1 3
b10010111 %
b10010111 4
b10010111 ;"
b10010100 '
b10010100 F
08"
b10010000 :
b10010000 i
b10100000 9
b10100000 j
b11110000 >
b11110000 e
b100000 =
b100000 f
b11000000 <
b11000000 g
b11110000 ;
b11110000 h
b1000000 @
b1000000 c
b10010000 ?
b10010000 d
1!
#115001
0!
#120001
05"
b0 $
b0 3
b10010000 Z
b10010000 /"
b110000 \
b110000 1"
b1100000 [
b1100000 0"
b100000 ]
b100000 2"
b1010000 #"
b1100000000000 -"
b110000 %"
b110000 )"
b1000000 ""
b1101000000000000 ."
b1100000 $"
b1100000 *"
b111000 &
b111000 5
b111000 Q
08
1D
b1100100000000000 !"
b1110000 1
b1110000 X
b1110000 z
b1110000 ?"
b11100000000000 ~
b10010000 2
b10010000 Y
b10010000 {
b10010000 C"
b0 A
b0 H
b0 4"
b0 :"
b0 7"
18"
1!
#125001
0!
#130001
b1101 '
b1101 F
b1100 &
b1100 5
b1100 Q
08"
b100000 :
b100000 i
b110000 9
b110000 j
b1100000 >
b1100000 e
b10010000 =
b10010000 f
b110000 <
b110000 g
b10000000 ;
b10000000 h
b11010000 @
b11010000 c
b0 ?
b0 d
0D
1E
1!
#135001
0!
#140001
b1101100 &
b1101100 5
b1101100 Q
1B
0E
1!
#145001
0!
#150001
b11111111 (
b11111111 6
17
16"
b10 $
b10 3
1!
#155001
0!
#160001
06"
b0 $
b0 3
b0 (
b0 6
b1111100 &
b1111100 5
b1111100 Q
b10010110 '
b10010110 F
07
b1 C
b1 G
19"
1!
#165001
0!
#170001
b11111111 (
b11111111 6
17
16"
b10 $
b10 3
09"
1!
#175001
0!
#180001
06"
b0 $
b0 3
b0 (
b0 6
b1110 &
b1110 5
b1110 Q
b10000011 '
b10000011 F
07
b10 C
b10 G
19"
1!
#185001
0!
#190001
b11111111 (
b11111111 6
17
16"
b10 $
b10 3
09"
1!
#195001
0!
#200001
06"
b0 $
b0 3
b0 (
b0 6
b1101100 &
b1101100 5
b1101100 Q
b110010 '
b110010 F
07
b11 C
b11 G
19"
1!
#205001
0!
#210001
b11111111 (
b11111111 6
17
16"
b10 $
b10 3
09"
1!
#215001
0!
#220001
06"
b0 $
b0 3
b0 (
b0 6
b1101 '
b1101 F
b1100 &
b1100 5
b1100 Q
07
b0 C
b0 G
0B
19"
1!
#225001
0!
#230001
09"
1!
#230002
b0 [
b0 0"
b0 ]
b0 2"
b0 Z
b0 /"
b0 \
b0 1"
b0 '
b0 F
b0 #"
b0 -"
b0 %"
b0 )"
b0 ""
b0 ."
b0 $"
b0 *"
b0 t
b0 v
b0 '"
b0 s
b0 u
b0 ("
b0 :
b0 i
b0 9
b0 j
b0 <
b0 g
b0 ;
b0 h
b0 >
b0 e
b0 =
b0 f
b0 @
b0 c
b0 !"
b0 1
b0 X
b0 z
b0 ?"
b0 ~
b0 2
b0 Y
b0 {
b0 C"
b0 r
b0 /
b0 V
b0 m
b0 >"
b0 q
b0 0
b0 W
b0 n
b0 B"
b0 -
b0 T
b0 x
b0 ="
b0 .
b0 U
b0 y
b0 A"
b0 +
b0 R
b0 k
b0 <"
b0 ,
b0 S
b0 l
b0 @"
b100 E"
1*
b0 %
b0 4
b0 ;"
0"
0#
b11 )
#235002
0!
#240002
b100 E"
1!
#245002
0!
#250002
0*
1#
b100 E"
1!
#255002
0!
#260002
18
15"
b1 $
b1 3
b10000 %
b10000 4
b10000 ;"
1"
1!
#265002
0!
#270002
05"
b0 $
b0 3
b10000 Z
b10000 /"
b10000 \
b10000 1"
b10000 s
b10000 u
b10000 ("
b1011010 &
b1011010 5
b1011010 Q
08
b10000 ,
b10000 S
b10000 l
b10000 @"
b1 A
b1 H
b1 4"
b1 :"
b1 7"
18"
1!
#275002
0!
#280002
18
15"
b1 $
b1 3
b0 %
b0 4
b0 ;"
b10000 '
b10000 F
08"
b10000 9
b10000 j
b10000 =
b10000 f
b10000 ;
b10000 h
b10000 ?
b10000 d
1!
#285002
0!
#290002
05"
b0 $
b0 3
b1001110 &
b1001110 5
b1001110 Q
08
b10 A
b10 H
b10 4"
b10 :"
b10 7"
18"
1!
#295002
0!
#300002
18
15"
b1 $
b1 3
08"
1!
#305002
0!
#310002
05"
b0 $
b0 3
b0 &
b0 5
b0 Q
08
b11 A
b11 H
b11 4"
b11 :"
b11 7"
18"
1!
#315002
0!
#320002
18
15"
b1 $
b1 3
08"
1!
#325002
0!
#330002
05"
b0 $
b0 3
b111000 &
b111000 5
b111000 Q
08
1D
b0 A
b0 H
b0 4"
b0 :"
b0 7"
18"
1!
#335002
0!
#340002
b1100 &
b1100 5
b1100 Q
08"
0D
1E
1!
#345002
0!
#350002
b1101100 &
b1101100 5
b1101100 Q
1B
0E
1!
#355002
0!
#360002
b11111111 (
b11111111 6
17
16"
b10 $
b10 3
1!
#365002
0!
#370002
06"
b0 $
b0 3
b0 (
b0 6
b1111100 &
b1111100 5
b1111100 Q
07
b1 C
b1 G
19"
1!
#375002
0!
#380002
b11111111 (
b11111111 6
17
16"
b10 $
b10 3
09"
1!
#385002
0!
#390002
06"
b0 $
b0 3
b0 (
b0 6
b1110 &
b1110 5
b1110 Q
07
b10 C
b10 G
19"
1!
#395002
0!
#400002
b11111111 (
b11111111 6
17
16"
b10 $
b10 3
09"
1!
#405002
0!
#410002
06"
b0 $
b0 3
b0 (
b0 6
b1101100 &
b1101100 5
b1101100 Q
07
b11 C
b11 G
19"
1!
#415002
0!
#420002
b11111111 (
b11111111 6
17
16"
b10 $
b10 3
09"
1!
#425002
0!
#430002
06"
b0 $
b0 3
b0 (
b0 6
b1100 &
b1100 5
b1100 Q
07
b0 C
b0 G
0B
19"
1!
#435002
0!
#440002
09"
1!
#440003
b0 Z
b0 /"
b0 \
b0 1"
b0 '
b0 F
b0 s
b0 u
b0 ("
b0 9
b0 j
b0 ;
b0 h
b0 =
b0 f
b0 ?
b0 d
b0 ,
b0 S
b0 l
b0 @"
b100 E"
1*
0"
0#
b100 )
#445003
0!
#450003
b100 E"
1!
#455003
0!
#460003
0*
1#
b100 E"
1!
#465003
0!
#470003
18
15"
b1 $
b1 3
b10000 %
b10000 4
b10000 ;"
1"
1!
#475003
0!
#480003
05"
b0 $
b0 3
b10000 Z
b10000 /"
b10000 \
b10000 1"
b10000 s
b10000 u
b10000 ("
b1011010 &
b1011010 5
b1011010 Q
08
b10000 ,
b10000 S
b10000 l
b10000 @"
b1 A
b1 H
b1 4"
b1 :"
b1 7"
18"
1!
#485003
0!
#490003
18
15"
b1 $
b1 3
b10000 '
b10000 F
08"
b10000 9
b10000 j
b10000 =
b10000 f
b10000 ;
b10000 h
b10000 ?
b10000 d
1!
#495003
0!
#500003
05"
b0 $
b0 3
b11110000 [
b11110000 0"
b10000 ]
b10000 2"
b10000 ""
b1111100000000000 ."
b10000 $"
b10000 *"
b1001110 &
b1001110 5
b1001110 Q
08
b10000 .
b10000 U
b10000 y
b10000 A"
b10 A
b10 H
b10 4"
b10 :"
b10 7"
18"
1!
#505003
0!
#510003
18
15"
b1 $
b1 3
b100000 '
b100000 F
08"
b10000 :
b10000 i
b11110000 >
b11110000 e
b0 ;
b0 h
b100000 ?
b100000 d
1!
#515003
0!
#520003
05"
b0 $
b0 3
b100000 Z
b100000 /"
b100000 \
b100000 1"
b0 s
b100000 u
b100000 ("
b0 &
b0 5
b0 Q
08
b1111100000000000 q
b10000 0
b10000 W
b10000 n
b10000 B"
b11 A
b11 H
b11 4"
b11 :"
b11 7"
18"
1!
#525003
0!
#530003
18
15"
b1 $
b1 3
b10000 '
b10000 F
08"
b100000 9
b100000 j
b100000 =
b100000 f
b11110000 ;
b11110000 h
b10000 ?
b10000 d
1!
#535003
0!
#540003
05"
b0 $
b0 3
b11100000 [
b11100000 0"
b100000 ]
b100000 2"
b0 ""
b1111000000000000 ."
b100000 $"
b100000 *"
b111000 &
b111000 5
b111000 Q
08
1D
b1111100000000000 ~
b10000 2
b10000 Y
b10000 {
b10000 C"
b0 A
b0 H
b0 4"
b0 :"
b0 7"
18"
1!
#545003
0!
#550003
b0 '
b0 F
b1100 &
b1100 5
b1100 Q
08"
b100000 :
b100000 i
b11100000 >
b11100000 e
b0 ;
b0 h
b0 ?
b0 d
0D
1E
1!
#555003
0!
#560003
b1101100 &
b1101100 5
b1101100 Q
1B
0E
1!
#565003
0!
#570003
b11111111 (
b11111111 6
17
16"
b10 $
b10 3
1!
#575003
0!
#580003
06"
b0 $
b0 3
b0 (
b0 6
b1111100 &
b1111100 5
b1111100 Q
b101110 '
b101110 F
07
b1 C
b1 G
19"
1!
#585003
0!
#590003
b11111111 (
b11111111 6
17
16"
b10 $
b10 3
09"
1!
#595003
0!
