src/switch_interface.sv
module switch_interface #(
    parameter DEBOUNCE_BITS = 16,
    parameter DEBOUNCE_MAX = 16'd50000 // 1ms assuming 50 MHz clock
)(
    input  logic clk,
    input  logic rst,
    input  logic sw_in,
    output logic pulse_out
);
            
    logic [DEBOUNCE_BITS-1:0] debounce_counter;
    logic state_debounced;
    logic state_prev;
    
    always_ff @(posedge clk or posedge rst) begin
        if (rst) begin
            debounce_counter <= '0;
            state_debounced  <= 1'b0;
            state_prev       <= 1'b0;
        end else begin
            state_prev <= state_debounced;
            
            if (sw_in != state_debounced) begin
                debounce_counter <= debounce_counter + 1;
                if (debounce_counter == DEBOUNCE_MAX) begin
                    state_debounced <= ~state_debounced;
                    debounce_counter <= '0;
                end
            end else begin
                debounce_counter <= '0;
            end
        end
    end
    
    assign pulse_out = state_debounced & ~state_prev; // Rising edge detection

endmodule

test/switch_interface/switch_tb.sv
`default_nettype none
`timescale 1ns / 1ps

module switch_tb ();

  // Dump the signals to a VCD file
  string vcd_name;
  initial begin
`ifdef VCD_PATH
    vcd_name = `VCD_PATH;
`else
    vcd_name = {"switch_tb_", `TIMESTAMP, ".vcd"};
`endif
    $dumpfile(vcd_name);
    $dumpvars(0, switch_tb);
    #1;
  end

  // Clock and control signals
  logic clk;
  logic rst;
  
  // Input signals
  wire sw_in;

  // Output signals
  wire pulse_out;

  // DUT
  switch_interface #(
      .DEBOUNCE_BITS(16),
      .DEBOUNCE_MAX(16'd5)  // Small value for fast test
  ) dut (
      .clk(clk),
      .rst(rst),
      .sw_in(sw_in),
      .pulse_out(pulse_out)
  );

endmodule

test/switch_interface/wave/switch_tb_20250623_02:10:19.vcd
$date
	Mon Jun 23 02:28:13 2025
$end
$version
	Icarus Verilog
$end
$timescale
	1ps
$end
$scope module switch_tb $end
$var wire 1 ! sw_in $end
$var wire 1 " pulse_out $end
$var reg 1 # clk $end
$var reg 1 $ rst $end
$scope module dut $end
$var wire 1 # clk $end
$var wire 1 " pulse_out $end
$var wire 1 $ rst $end
$var wire 1 ! sw_in $end
$var reg 16 % debounce_counter [15:0] $end
$var reg 1 & state_debounced $end
$var reg 1 ' state_prev $end
$upscope $end
$upscope $end
$enddefinitions $end
#0
$dumpvars
0'
0&
b0 %
0$
1#
0"
z!
$end
#5000
0#
#10000
0!
1#
#15000
0#
#20000
1#
#25000
0#
#30000
1!
1#
#35000
0#
#40000
b1 %
1#
#45000
0#
#50000
b10 %
1#
#55000
0#
#60000
b11 %
1#
#65000
0#
#70000
b100 %
1#
#75000
0#
#80000
b101 %
1#
#85000
0#
#90000
1"
1&
b0 %
1#
#95000
0#
#100000
0"
1'
1#
#105000
0#
#110000
1#
#115000
0#
#120000
1#
#125000
0#
#130000
1#
#135000
0#
#140000
1#
#145000
0#
#150000
1#
#155000
0#
#160000
1#
#165000
0#
#170000
1#
#175000
0#
#180000
1#
#185000
0#
#190000
1#
#195000
0#
#200000
b1 %
1#
0!
#205000
0#
#210000
b10 %
1#
#215000
0#
#220000
b11 %
1#
#225000
0#
#230000
b100 %
1#
#235000
0#
#240000
b101 %
1#
#245000
0#
#250000
0&
b0 %
1#
#255000
0#
#260000
0'
1#
#265000
0#
#270000
1#
#275000
0#
#280000
1#
#285000
0#
#290000
1#
#295000
0#
#300000
1#
#305000
0#
#310000
1!
1#
#313000
0!
#315000
0#
#316000
1!
#319000
0!
#320000
1#
#322000
1!
#325000
0!
0#
#328000
1!
#330000
b1 %
1#
#335000
0#
#340000
b10 %
1#
#345000
0#
#350000
b11 %
1#
#355000
0#
#360000
b100 %
1#
#365000
0#
#370000
b101 %
1#
#375000
0#
#380000
1"
1&
b0 %
1#
#385000
0#
#390000
0"
1'
1#
#395000
0#
#400000
1#
#405000
0#
#410000
1#
#415000
0#
#420000
1#
#425000
0#
#430000
1#
#435000
0#
#440000
1#
#445000
0#
#450000
1#
#455000
0#
#460000
1#
#465000
0#
#470000
1#
#475000
0#
#480000
1#
#485000
0#
#490000
1#
#495000
0#
#500000
1#
#505000
0#
#510000
1#
#515000
0#
#520000
0!
1#
#525000
0#
#530000
b1 %
1#
#535000
0#
#540000
b10 %
1#
#545000
0#
#550000
b11 %
1#
#555000
0#
#560000
b100 %
1#
#565000
0#
#570000
b101 %
1#
#575000
0#
#580000
0&
b0 %
1#
#585000
0#
#590000
0'
1#
