src/fft_memory.sv
module fft_memory (
    input  logic        clk,
    input  logic        rst,            // synch reset (see if we want to change this to async)
    input  logic        en,             // read enable (1 = read/write, 0 = hold previous outputs)
    input  logic        write_en,       // write enable (only used when en = 1)
    input  logic  [1:0] addr_w,         // write address
    input  logic [15:0] data_in,        // data to write

    input  logic  [1:0] addr_a,         // read port A address
    output logic [15:0] data_out_a,     // read port A output

    input  logic  [1:0] addr_b,         // read port B address
    output logic [15:0] data_out_b,     // read port B output

    output logic        read_valid           // output is valid when high (1 cycle after en=1)
);

    // 4-word x 16-bit memory
    logic [15:0] mem [0:3];

    // internal data registers for read outputs
    logic [15:0] reg_a, reg_b;
    logic        valid;

    always_ff @(posedge clk or posedge rst) begin
        if (rst) begin
            mem[0] <= 16'd0;
            mem[1] <= 16'd0;
            mem[2] <= 16'd0;
            mem[3] <= 16'd0;
            reg_a  <= 16'd0;
            reg_b  <= 16'd0;
            valid  <= 1'b0;
        end else if (en) begin

            if (write_en) begin
                mem[addr_w] <= data_in;
            end

            reg_a <= mem[addr_a];
            reg_b <= mem[addr_b];
            
            // valid is high only if en is high and write_en is low
            valid <= !write_en;

        end else begin
            valid <= 1'b0;
        end
    end

    //dual port read outputs
    assign data_out_a = reg_a;
    assign data_out_b = reg_b;
    assign read_valid = valid;


endmodule

test/memory_test/memory_tb.sv
`default_nettype none
`timescale 1ns / 1ps

module memory_tb;

  // Dump the signals to a VCD file
  string vcd_name;
  initial begin
`ifdef VCD_PATH
    vcd_name = `VCD_PATH;
`else
    vcd_name = {"memory_tb_", `TIMESTAMP, ".vcd"};
`endif
    $dumpfile(vcd_name);
    $dumpvars(0, memory_tb);
    #1;
  end

  // Clock and control signals
  reg clk;
  reg rst;
  reg en;
  reg write_en;
  
  // Write port signals
  reg [1:0] addr_w;
  reg [15:0] data_in;
  
  // Read port A signals
  reg [1:0] addr_a;
  wire [15:0] data_out_a;
  
  // Read port B signals
  reg [1:0] addr_b;
  wire [15:0] data_out_b;
  
  // Output valid signal
  wire read_valid;

  // Instantiate the memory module (DUT)
  fft_memory dut (
      .clk(clk),
      .rst(rst),
      .en(en),
      .write_en(write_en),
      .addr_w(addr_w),
      .data_in(data_in),
      .addr_a(addr_a),
      .data_out_a(data_out_a),
      .addr_b(addr_b),
      .data_out_b(data_out_b),
      .read_valid(read_valid)
  );

endmodule

test/memory_test/wave/memory_tb_20250623_16:18:29.vcd
$date
	Mon Jun 23 16:18:32 2025
$end
$version
	Icarus Verilog
$end
$timescale
	1ps
$end
$scope module memory_tb $end
$var wire 1 ! read_valid $end
$var wire 16 " data_out_b [15:0] $end
$var wire 16 # data_out_a [15:0] $end
$var reg 2 $ addr_a [1:0] $end
$var reg 2 % addr_b [1:0] $end
$var reg 2 & addr_w [1:0] $end
$var reg 1 ' clk $end
$var reg 16 ( data_in [15:0] $end
$var reg 1 ) en $end
$var reg 1 * rst $end
$var reg 1 + write_en $end
$scope module dut $end
$var wire 2 , addr_a [1:0] $end
$var wire 2 - addr_b [1:0] $end
$var wire 2 . addr_w [1:0] $end
$var wire 1 ' clk $end
$var wire 16 / data_in [15:0] $end
$var wire 16 0 data_out_a [15:0] $end
$var wire 16 1 data_out_b [15:0] $end
$var wire 1 ) en $end
$var wire 1 ! read_valid $end
$var wire 1 * rst $end
$var wire 1 + write_en $end
$var reg 16 2 reg_a [15:0] $end
$var reg 16 3 reg_b [15:0] $end
$var reg 1 4 valid $end
$upscope $end
$upscope $end
$enddefinitions $end
$comment Show the parameter values. $end
$dumpall
$end
#0
$dumpvars
04
b0 3
b0 2
b0 1
b0 0
bx /
bx .
bx -
bx ,
x+
0*
x)
bx (
1'
bx &
bx %
bx $
b0 #
b0 "
0!
$end
#5000
0'
#10000
b1001000110100 (
b1001000110100 /
b0 &
b0 .
1+
1)
1'
#15000
0'
#20000
b0 $
b0 ,
0+
bx "
bx 1
bx 3
bx #
bx 0
bx 2
1'
#25000
0'
#30000
1!
14
b1001000110100 #
b1001000110100 0
b1001000110100 2
1'
#35000
0'
#40000
0)
1'
#45000
0'
#50000
0!
04
1'
#50001
b0 "
b0 1
b0 3
b0 #
b0 0
b0 2
1*
#55001
0'
#60001
0*
1'
#65001
0'
#70001
1+
1)
1'
#75001
0'
#80001
b101011001111000 (
b101011001111000 /
b1 &
b1 .
bx "
bx 1
bx 3
1'
#85001
0'
#90001
b1001101010111100 (
b1001101010111100 /
b10 &
b10 .
b1001000110100 #
b1001000110100 0
b1001000110100 2
1'
#95001
0'
#100001
b1101111011110000 (
b1101111011110000 /
b11 &
b11 .
1'
#105001
0'
#110001
0+
1'
#115001
0'
#120001
1!
14
1'
#125001
0'
#130001
b1 $
b1 ,
1'
#135001
0'
#140001
b101011001111000 #
b101011001111000 0
b101011001111000 2
1'
#145001
0'
#150001
b10 $
b10 ,
1'
#155001
0'
#160001
b1001101010111100 #
b1001101010111100 0
b1001101010111100 2
1'
#165001
0'
#170001
b11 $
b11 ,
1'
#175001
0'
#180001
b1101111011110000 #
b1101111011110000 0
b1101111011110000 2
1'
#185001
0'
#190001
1'
#190002
0!
04
b0 "
b0 1
b0 3
b0 #
b0 0
b0 2
1*
#195002
0'
#200002
0*
1'
#205002
0'
#210002
b0 $
b0 ,
1!
14
bx "
bx 1
bx 3
1'
#215002
0'
#220002
1'
#225002
0'
#230002
b1 $
b1 ,
1'
#235002
0'
#240002
1'
#245002
0'
#250002
b10 $
b10 ,
1'
#255002
0'
#260002
1'
#265002
0'
#270002
b11 $
b11 ,
1'
#275002
0'
#280002
1'
#285002
0'
#290002
1'
#290003
0!
04
b0 "
b0 1
b0 3
1*
#295003
0'
#300003
0*
1'
#305003
0'
#310003
b1111111111111111 (
b1111111111111111 /
b0 &
b0 .
1+
1!
14
bx "
bx 1
bx 3
1'
#315003
0'
#320003
b1 &
b1 .
0!
04
1'
#325003
0'
#330003
b10 &
b10 .
1'
#335003
0'
#340003
b11 &
b11 .
1'
#345003
0'
#350003
b0 (
b0 /
b0 &
b0 .
1'
#355003
0'
#360003
b1 &
b1 .
b1111111111111111 #
b1111111111111111 0
b1111111111111111 2
1'
#365003
0'
#370003
b10 &
b10 .
1'
#375003
0'
#380003
b11 &
b11 .
1'
#385003
0'
#390003
b0 $
b0 ,
0+
1'
#395003
0'
#400003
1!
14
b0 #
b0 0
b0 2
1'
#405003
0'
#410003
b1 $
b1 ,
1'
#415003
0'
#420003
1'
#425003
0'
#430003
b10 $
b10 ,
1'
#435003
0'
#440003
1'
#445003
0'
#450003
b11 $
b11 ,
1'
#455003
0'
#460003
1'
#465003
0'
#470003
1'
#470004
0!
04
b0 "
b0 1
b0 3
1*
#475004
0'
#480004
0*
1'
#485004
0'
#490004
b0 $
b0 ,
1!
14
bx "
bx 1
bx 3
1'
#495004
0'
#500004
1'
#505004
0'
#510004
b1 $
b1 ,
1'
#515004
0'
#520004
1'
#525004
0'
#530004
b10 $
b10 ,
1'
#535004
0'
#540004
1'
#545004
0'
#550004
b11 $
b11 ,
1'
#555004
0'
#560004
1'
#565004
0'
#570004
1'
#570005
0!
04
b0 "
b0 1
b0 3
1*
#575005
0'
#580005
0*
1'
#585005
0'
#590005
1!
14
bx "
bx 1
bx 3
1'
#595005
0'
#600005
1'
#605005
0'
#610005
b1 $
b1 ,
1'
#615005
0'
#620005
1'
#625005
0'
#630005
b0 $
b0 ,
1'
#635005
0'
#640005
1'
#645005
0'
#650005
1'
#655005
0'
#660005
1'
#665005
0'
#670005
b10 $
b10 ,
1'
#675005
0'
#680005
1'
#685005
0'
#690005
b11 $
b11 ,
1'
#695005
0'
#700005
1'
#705005
0'
#710005
b10 $
b10 ,
1'
#715005
0'
#720005
1'
#725005
0'
#730005
b1 $
b1 ,
1'
#735005
0'
#740005
1'
#745005
0'
#750005
1'
#755005
0'
#760005
1'
#765005
0'
#770005
b10 $
b10 ,
1'
#775005
0'
#780005
1'
#785005
0'
#790005
1'
#790006
0!
04
b0 "
b0 1
b0 3
1*
#795006
0'
#800006
0*
1'
#805006
0'
#810006
b1000000000000 (
b1000000000000 /
b0 &
b0 .
1+
1!
14
bx "
bx 1
bx 3
1'
#815006
0'
#820006
b1000000000001 (
b1000000000001 /
b1 &
b1 .
0!
04
1'
#825006
0'
#830006
b1000000000010 (
b1000000000010 /
b10 &
b10 .
1'
#835006
0'
#840006
b1000000000011 (
b1000000000011 /
b11 &
b11 .
1'
#845006
0'
#850006
b1001100110011001 (
b1001100110011001 /
b10 &
b10 .
b1000000000010 #
b1000000000010 0
b1000000000010 2
1'
#855006
0'
#860006
b0 $
b0 ,
0+
1'
#865006
0'
#870006
1!
14
b1000000000000 #
b1000000000000 0
b1000000000000 2
1'
#875006
0'
#880006
b1 $
b1 ,
1'
#885006
0'
#890006
b1000000000001 #
b1000000000001 0
b1000000000001 2
1'
#895006
0'
#900006
b10 $
b10 ,
1'
#905006
0'
#910006
b1001100110011001 #
b1001100110011001 0
b1001100110011001 2
1'
#915006
0'
#920006
b11 $
b11 ,
1'
#925006
0'
#930006
b1000000000011 #
b1000000000011 0
b1000000000011 2
1'
#935006
0'
#940006
1'
#940007
0!
04
b0 "
b0 1
b0 3
b0 #
b0 0
b0 2
1*
#945007
0'
#950007
0*
1'
#955007
0'
#960007
b1000100010001 (
b1000100010001 /
b0 &
b0 .
1+
1!
14
bx "
bx 1
bx 3
1'
#965007
0'
#970007
b10001000100010 (
b10001000100010 /
b1 &
b1 .
0!
04
1'
#975007
0'
#980007
b11001100110011 (
b11001100110011 /
b10 &
b10 .
1'
#985007
0'
#990007
b100010001000100 (
b100010001000100 /
b11 &
b11 .
1'
#995007
0'
#1000007
b1 %
b1 -
b0 $
b0 ,
0+
1'
#1005007
0'
#1010007
1!
14
b10001000100010 "
b10001000100010 1
b10001000100010 3
b1000100010001 #
b1000100010001 0
b1000100010001 2
1'
#1015007
0'
#1020007
b10 %
b10 -
b1 $
b1 ,
1'
#1025007
0'
#1030007
b11001100110011 "
b11001100110011 1
b11001100110011 3
b10001000100010 #
b10001000100010 0
b10001000100010 2
1'
#1035007
0'
#1040007
b11 %
b11 -
b10 $
b10 ,
1'
#1045007
0'
#1050007
b100010001000100 "
b100010001000100 1
b100010001000100 3
b11001100110011 #
b11001100110011 0
b11001100110011 2
1'
#1055007
0'
#1060007
b0 %
b0 -
b11 $
b11 ,
1'
#1065007
0'
#1070007
b1000100010001 "
b1000100010001 1
b1000100010001 3
b100010001000100 #
b100010001000100 0
b100010001000100 2
1'
#1075007
0'
#1080007
1'
#1080008
0!
04
b0 "
b0 1
b0 3
b0 #
b0 0
b0 2
1*
#1085008
0'
#1090008
0*
1'
#1095008
0'
#1100008
b1010101010101010 (
b1010101010101010 /
b0 &
b0 .
1+
1!
14
1'
#1105008
0'
#1110008
b1010101010101011 (
b1010101010101011 /
b1 &
b1 .
0!
04
1'
#1115008
0'
#1120008
b1010101010101100 (
b1010101010101100 /
b10 &
b10 .
b1010101010101010 "
b1010101010101010 1
b1010101010101010 3
1'
#1125008
0'
#1130008
b1010101010101101 (
b1010101010101101 /
b11 &
b11 .
1'
#1135008
0'
#1140008
b0 $
b0 ,
0+
1'
#1145008
0'
#1150008
1!
14
b1010101010101010 #
b1010101010101010 0
b1010101010101010 2
1'
#1155008
0'
#1160008
b1 $
b1 ,
1'
#1165008
0'
#1170008
b1010101010101011 #
b1010101010101011 0
b1010101010101011 2
1'
#1175008
0'
#1180008
b10 $
b10 ,
1'
#1185008
0'
#1190008
b1010101010101100 #
b1010101010101100 0
b1010101010101100 2
1'
#1195008
0'
#1200008
b11 $
b11 ,
1'
#1205008
0'
#1210008
b1010101010101101 #
b1010101010101101 0
b1010101010101101 2
1'
#1215008
0'
#1220008
0!
04
b0 "
b0 1
b0 3
b0 #
b0 0
b0 2
1*
1'
#1225008
0'
#1230008
0*
1'
#1235008
0'
#1240008
b0 $
b0 ,
1!
14
1'
#1245008
0'
#1250008
1'
#1255008
0'
#1260008
b1 $
b1 ,
1'
#1265008
0'
#1270008
1'
#1275008
0'
#1280008
b10 $
b10 ,
1'
#1285008
0'
#1290008
1'
#1295008
0'
#1300008
b11 $
b11 ,
1'
#1305008
0'
#1310008
1'
#1315008
0'
#1320008
1'
#1320009
0!
04
1*
#1325009
0'
#1330009
0*
1'
#1335009
0'
#1340009
b1000100010001 (
b1000100010001 /
b0 &
b0 .
1+
1!
14
1'
#1345009
0'
#1350009
b10001000100010 (
b10001000100010 /
b1 &
b1 .
0!
04
1'
#1355009
0'
#1360009
b11001100110011 (
b11001100110011 /
b10 &
b10 .
b1000100010001 "
b1000100010001 1
b1000100010001 3
1'
#1365009
0'
#1370009
b100010001000100 (
b100010001000100 /
b11 &
b11 .
1'
#1375009
0'
#1380009
b10 %
b10 -
b0 $
b0 ,
0+
1'
#1385009
0'
#1390009
1!
14
b11001100110011 "
b11001100110011 1
b11001100110011 3
b1000100010001 #
b1000100010001 0
b1000100010001 2
1'
#1395009
0'
#1400009
b1 %
b1 -
b1 $
b1 ,
1'
#1405009
0'
#1410009
b10001000100010 "
b10001000100010 1
b10001000100010 3
b10001000100010 #
b10001000100010 0
b10001000100010 2
1'
#1415009
0'
#1420009
1'
#1420010
0!
04
b0 "
b0 1
b0 3
b0 #
b0 0
b0 2
1*
#1425010
0'
#1430010
0*
1'
#1435010
0'
#1440010
b1000000000000 (
b1000000000000 /
b0 &
b0 .
1+
1!
14
1'
#1445010
0'
#1450010
b1000000000001 (
b1000000000001 /
b1 &
b1 .
0!
04
1'
#1455010
0'
#1460010
b1000000000010 (
b1000000000010 /
b10 &
b10 .
1'
#1465010
0'
#1470010
b1000000000011 (
b1000000000011 /
b11 &
b11 .
b1000000000001 "
b1000000000001 1
b1000000000001 3
b1000000000001 #
b1000000000001 0
b1000000000001 2
1'
#1475010
0'
#1480010
1'
#1480011
b0 "
b0 1
b0 3
b0 #
b0 0
b0 2
1*
#1485011
0'
#1490011
0*
1'
#1495011
0'
#1500011
b0 (
b0 /
b0 &
b0 .
1'
#1505011
0'
#1510011
b1111111111111111 (
b1111111111111111 /
b1 &
b1 .
1'
#1515011
0'
#1520011
b1000000000000000 (
b1000000000000000 /
b10 &
b10 .
1'
#1525011
0'
#1530011
b111111111111111 (
b111111111111111 /
b11 &
b11 .
b1111111111111111 "
b1111111111111111 1
b1111111111111111 3
b1111111111111111 #
b1111111111111111 0
b1111111111111111 2
1'
#1535011
0'
#1540011
b0 $
b0 ,
0+
1'
#1545011
0'
#1550011
1!
14
b0 #
b0 0
b0 2
1'
#1555011
0'
#1560011
b1 $
b1 ,
1'
#1565011
0'
#1570011
b1111111111111111 #
b1111111111111111 0
b1111111111111111 2
1'
#1575011
0'
#1580011
b10 $
b10 ,
1'
#1585011
0'
#1590011
b1000000000000000 #
b1000000000000000 0
b1000000000000000 2
1'
#1595011
0'
#1600011
b11 $
b11 ,
1'
#1605011
0'
#1610011
b111111111111111 #
b111111111111111 0
b111111111111111 2
1'
#1615011
0'
#1620011
1'
#1620012
0!
04
b0 "
b0 1
b0 3
b0 #
b0 0
b0 2
1*
#1625012
0'
#1630012
0*
1'
#1635012
0'
#1640012
b1000100010001 (
b1000100010001 /
b0 &
b0 .
1+
1!
14
1'
#1645012
0'
#1650012
0!
04
1'
