src/fft_memory.sv
module fft_memory (
    input  logic        clk,
    input  logic        rst,            // synch reset (see if we want to change this to async)
    input  logic        en,             // general enable (1 = read/write operations allowed, 0 = hold outputs)
    input  logic        read_en,        // read enable (1 = perform read, 0 = no read)
    input  logic        write_en,       // write enable (1 = perform write, 0 = no write)
    input  logic  [1:0] addr_w,         // write address
    input  logic [15:0] data_in,        // data to write

    input  logic  [1:0] addr_a,         // read port A address
    output logic [15:0] data_out_a,     // read port A output

    input  logic  [1:0] addr_b,         // read port B address
    output logic [15:0] data_out_b,     // read port B output

    output logic        read_valid           // output is valid when high (en=1 AND read_en=1 AND write_en=0)
);

    // 4-word x 16-bit memory
    logic [15:0] mem [0:3];

    logic [15:0] reg_a, reg_b;
    logic        valid;

    always_ff @(posedge clk or posedge rst) begin
        if (rst) begin
            mem[0] <= 16'd0;
            mem[1] <= 16'd0;
            mem[2] <= 16'd0;
            mem[3] <= 16'd0;
            reg_a  <= 16'd0;
            reg_b  <= 16'd0;
            valid  <= 1'b0;
        end else if (en) begin
            if (write_en) begin
                mem[addr_w] <= data_in;
            end

            if (read_en && !write_en) begin
                reg_a <= mem[addr_a];
                reg_b <= mem[addr_b];
                valid <= 1'b1;
            end else if (read_en && write_en) begin
                reg_a <= reg_a;  // Hold previous value
                reg_b <= reg_b;  // Hold previous value
                valid <= 1'b0;   // Invalid during conflict
            end else begin
                valid <= 1'b0;
            end
        end else begin
            valid <= 1'b0;
        end
    end

    assign data_out_a = reg_a;
    assign data_out_b = reg_b;
    assign read_valid = valid;

endmodule

test/memory_test/memory_tb.sv
`default_nettype none
`timescale 1ns / 1ps

module memory_tb;

  // Dump the signals to a VCD file
  string vcd_name;
  initial begin
`ifdef VCD_PATH
    vcd_name = `VCD_PATH;
`else
    vcd_name = {"memory_tb_", `TIMESTAMP, ".vcd"};
`endif
    $dumpfile(vcd_name);
    $dumpvars(0, memory_tb);
    #1;
  end

  // Clock and control signals
  reg clk;
  reg rst;
  reg en;
  reg read_en;
  reg write_en;
  
  // Write port signals
  reg [1:0] addr_w;
  reg [15:0] data_in;
  
  // Read port A signals
  reg [1:0] addr_a;
  wire [15:0] data_out_a;
  
  // Read port B signals
  reg [1:0] addr_b;
  wire [15:0] data_out_b;
  
  // Output valid signal
  wire read_valid;

  // Test counter signal - will be set by Python test
  reg [7:0] test_counter;
  wire [7:0] current_test;

  // Assign the test counter to a wire for monitoring
  assign current_test = test_counter;

  // Instantiate the memory module (DUT)
  fft_memory dut (
      .clk(clk),
      .rst(rst),
      .en(en),
      .read_en(read_en),
      .write_en(write_en),
      .addr_w(addr_w),
      .data_in(data_in),
      .addr_a(addr_a),
      .data_out_a(data_out_a),
      .addr_b(addr_b),
      .data_out_b(data_out_b),
      .read_valid(read_valid)
  );

endmodule

test/memory_test/wave/memory_tb_20250623_16:46:49.vcd
$date
	Mon Jun 23 16:46:52 2025
$end
$version
	Icarus Verilog
$end
$timescale
	1ps
$end
$scope module memory_tb $end
$var wire 8 ! current_test [7:0] $end
$var wire 1 " read_valid $end
$var wire 16 # data_out_b [15:0] $end
$var wire 16 $ data_out_a [15:0] $end
$var reg 2 % addr_a [1:0] $end
$var reg 2 & addr_b [1:0] $end
$var reg 2 ' addr_w [1:0] $end
$var reg 1 ( clk $end
$var reg 16 ) data_in [15:0] $end
$var reg 1 * en $end
$var reg 1 + read_en $end
$var reg 1 , rst $end
$var reg 8 - test_counter [7:0] $end
$var reg 1 . write_en $end
$scope module dut $end
$var wire 2 / addr_a [1:0] $end
$var wire 2 0 addr_b [1:0] $end
$var wire 2 1 addr_w [1:0] $end
$var wire 1 ( clk $end
$var wire 16 2 data_in [15:0] $end
$var wire 16 3 data_out_a [15:0] $end
$var wire 16 4 data_out_b [15:0] $end
$var wire 1 * en $end
$var wire 1 + read_en $end
$var wire 1 " read_valid $end
$var wire 1 , rst $end
$var wire 1 . write_en $end
$var reg 16 5 reg_a [15:0] $end
$var reg 16 6 reg_b [15:0] $end
$var reg 1 7 valid $end
$upscope $end
$upscope $end
$enddefinitions $end
$comment Show the parameter values. $end
$dumpall
$end
#0
$dumpvars
07
b0 6
b0 5
b0 4
b0 3
bx 2
bx 1
bx 0
bx /
x.
b1 -
0,
x+
x*
bx )
1(
bx '
bx &
bx %
b0 $
b0 #
0"
b1 !
$end
#5000
0(
#10000
b1001000110100 )
b1001000110100 2
b0 '
b0 1
1.
1+
1*
1(
#15000
0(
#20000
b0 %
b0 /
0.
1(
#25000
0(
#30000
1"
17
bx #
bx 4
bx 6
b1001000110100 $
b1001000110100 3
b1001000110100 5
1(
#35000
0(
#40000
0*
1(
#45000
0(
#50000
0"
07
1(
#55000
0(
#60000
1(
#60001
b0 #
b0 4
b0 6
b0 $
b0 3
b0 5
1,
b10 !
b10 -
#65001
0(
#70001
0,
1(
#75001
0(
#80001
1.
0+
1*
1(
#85001
0(
#90001
b101011001111000 )
b101011001111000 2
b1 '
b1 1
1(
#95001
0(
#100001
b1001101010111100 )
b1001101010111100 2
b10 '
b10 1
1(
#105001
0(
#110001
b1101111011110000 )
b1101111011110000 2
b11 '
b11 1
1(
#115001
0(
#120001
1+
0.
1(
#125001
0(
#130001
1"
17
bx #
bx 4
bx 6
b1001000110100 $
b1001000110100 3
b1001000110100 5
1(
#135001
0(
#140001
b1 %
b1 /
1(
#145001
0(
#150001
b101011001111000 $
b101011001111000 3
b101011001111000 5
1(
#155001
0(
#160001
b10 %
b10 /
1(
#165001
0(
#170001
b1001101010111100 $
b1001101010111100 3
b1001101010111100 5
1(
#175001
0(
#180001
b11 %
b11 /
1(
#185001
0(
#190001
b1101111011110000 $
b1101111011110000 3
b1101111011110000 5
1(
#195001
0(
#200001
1(
#200002
0"
07
b0 #
b0 4
b0 6
b0 $
b0 3
b0 5
1,
b11 !
b11 -
#205002
0(
#210002
0,
1(
#215002
0(
#220002
b0 %
b0 /
1"
17
bx #
bx 4
bx 6
1(
#225002
0(
#230002
1(
#235002
0(
#240002
b1 %
b1 /
1(
#245002
0(
#250002
1(
#255002
0(
#260002
b10 %
b10 /
1(
#265002
0(
#270002
1(
#275002
0(
#280002
b11 %
b11 /
1(
#285002
0(
#290002
1(
#295002
0(
#300002
1(
#300003
0"
07
b0 #
b0 4
b0 6
1,
b100 !
b100 -
#305003
0(
#310003
0,
1(
#315003
0(
#320003
b1111111111111111 )
b1111111111111111 2
b0 '
b0 1
1.
0+
1"
17
bx #
bx 4
bx 6
1(
#325003
0(
#330003
b1 '
b1 1
0"
07
1(
#335003
0(
#340003
b10 '
b10 1
1(
#345003
0(
#350003
b11 '
b11 1
1(
#355003
0(
#360003
b0 )
b0 2
b0 '
b0 1
1(
#365003
0(
#370003
b1 '
b1 1
1(
#375003
0(
#380003
b10 '
b10 1
1(
#385003
0(
#390003
b11 '
b11 1
1(
#395003
0(
#400003
b0 %
b0 /
1+
0.
1(
#405003
0(
#410003
1"
17
1(
#415003
0(
#420003
b1 %
b1 /
1(
#425003
0(
#430003
1(
#435003
0(
#440003
b10 %
b10 /
1(
#445003
0(
#450003
1(
#455003
0(
#460003
b11 %
b11 /
1(
#465003
0(
#470003
1(
#475003
0(
#480003
1(
#480004
0"
07
b0 #
b0 4
b0 6
1,
b101 !
b101 -
#485004
0(
#490004
0,
1(
#495004
0(
#500004
b0 %
b0 /
1"
17
bx #
bx 4
bx 6
1(
#505004
0(
#510004
1(
#515004
0(
#520004
b1 %
b1 /
1(
#525004
0(
#530004
1(
#535004
0(
#540004
b10 %
b10 /
1(
#545004
0(
#550004
1(
#555004
0(
#560004
b11 %
b11 /
1(
#565004
0(
#570004
1(
#575004
0(
#580004
1(
#580005
0"
07
b0 #
b0 4
b0 6
1,
b110 !
b110 -
#585005
0(
#590005
0,
1(
#595005
0(
#600005
b0 %
b0 /
1"
17
bx #
bx 4
bx 6
1(
#605005
0(
#610005
1(
#615005
0(
#620005
b11 %
b11 /
1(
#625005
0(
#630005
1(
#635005
0(
#640005
b10 %
b10 /
1(
#645005
0(
#650005
1(
#655005
0(
#660005
b0 %
b0 /
1(
#665005
0(
#670005
1(
#675005
0(
#680005
b11 %
b11 /
1(
#685005
0(
#690005
1(
#695005
0(
#700005
1(
#705005
0(
#710005
1(
#715005
0(
#720005
b1 %
b1 /
1(
#725005
0(
#730005
1(
#735005
0(
#740005
b0 %
b0 /
1(
#745005
0(
#750005
1(
#755005
0(
#760005
b10 %
b10 /
1(
#765005
0(
#770005
1(
#775005
0(
#780005
b1 %
b1 /
1(
#785005
0(
#790005
1(
#795005
0(
#800005
1(
#800006
0"
07
b0 #
b0 4
b0 6
1,
b111 !
b111 -
#805006
0(
#810006
0,
1(
#815006
0(
#820006
b1000000000000 )
b1000000000000 2
b0 '
b0 1
1.
0+
1"
17
bx #
bx 4
bx 6
1(
#825006
0(
#830006
b1000000000001 )
b1000000000001 2
b1 '
b1 1
0"
07
1(
#835006
0(
#840006
b1000000000010 )
b1000000000010 2
b10 '
b10 1
1(
#845006
0(
#850006
b1000000000011 )
b1000000000011 2
b11 '
b11 1
1(
#855006
0(
#860006
b1001100110011001 )
b1001100110011001 2
b10 '
b10 1
1(
#865006
0(
#870006
b0 %
b0 /
1+
0.
1(
#875006
0(
#880006
1"
17
b1000000000000 $
b1000000000000 3
b1000000000000 5
1(
#885006
0(
#890006
b1 %
b1 /
1(
#895006
0(
#900006
b1000000000001 $
b1000000000001 3
b1000000000001 5
1(
#905006
0(
#910006
b10 %
b10 /
1(
#915006
0(
#920006
b1001100110011001 $
b1001100110011001 3
b1001100110011001 5
1(
#925006
0(
#930006
b11 %
b11 /
1(
#935006
0(
#940006
b1000000000011 $
b1000000000011 3
b1000000000011 5
1(
#945006
0(
#950006
1(
#950007
0"
07
b0 #
b0 4
b0 6
b0 $
b0 3
b0 5
1,
b1000 !
b1000 -
#955007
0(
#960007
0,
1(
#965007
0(
#970007
b1000100010001 )
b1000100010001 2
b0 '
b0 1
1.
0+
1"
17
bx #
bx 4
bx 6
1(
#975007
0(
#980007
b10001000100010 )
b10001000100010 2
b1 '
b1 1
0"
07
1(
#985007
0(
#990007
b11001100110011 )
b11001100110011 2
b10 '
b10 1
1(
#995007
0(
#1000007
b100010001000100 )
b100010001000100 2
b11 '
b11 1
1(
#1005007
0(
#1010007
b1 &
b1 0
b0 %
b0 /
1+
0.
1(
#1015007
0(
#1020007
1"
17
b10001000100010 #
b10001000100010 4
b10001000100010 6
b1000100010001 $
b1000100010001 3
b1000100010001 5
1(
#1025007
0(
#1030007
b10 &
b10 0
b1 %
b1 /
1(
#1035007
0(
#1040007
b11001100110011 #
b11001100110011 4
b11001100110011 6
b10001000100010 $
b10001000100010 3
b10001000100010 5
1(
#1045007
0(
#1050007
b11 &
b11 0
b10 %
b10 /
1(
#1055007
0(
#1060007
b100010001000100 #
b100010001000100 4
b100010001000100 6
b11001100110011 $
b11001100110011 3
b11001100110011 5
1(
#1065007
0(
#1070007
b0 &
b0 0
b11 %
b11 /
1(
#1075007
0(
#1080007
b1000100010001 #
b1000100010001 4
b1000100010001 6
b100010001000100 $
b100010001000100 3
b100010001000100 5
1(
#1085007
0(
#1090007
1(
#1090008
0"
07
b0 #
b0 4
b0 6
b0 $
b0 3
b0 5
1,
b1001 !
b1001 -
#1095008
0(
#1100008
0,
1(
#1105008
0(
#1110008
b1010101010101010 )
b1010101010101010 2
b0 '
b0 1
1.
0+
1"
17
1(
#1115008
0(
#1120008
b1010101010101011 )
b1010101010101011 2
b1 '
b1 1
0"
07
1(
#1125008
0(
#1130008
b1010101010101100 )
b1010101010101100 2
b10 '
b10 1
1(
#1135008
0(
#1140008
b1010101010101101 )
b1010101010101101 2
b11 '
b11 1
1(
#1145008
0(
#1150008
b0 %
b0 /
1+
0.
1(
#1155008
0(
#1160008
1"
17
b1010101010101010 #
b1010101010101010 4
b1010101010101010 6
b1010101010101010 $
b1010101010101010 3
b1010101010101010 5
1(
#1165008
0(
#1170008
b1 %
b1 /
1(
#1175008
0(
#1180008
b1010101010101011 $
b1010101010101011 3
b1010101010101011 5
1(
#1185008
0(
#1190008
b10 %
b10 /
1(
#1195008
0(
#1200008
b1010101010101100 $
b1010101010101100 3
b1010101010101100 5
1(
#1205008
0(
#1210008
b11 %
b11 /
1(
#1215008
0(
#1220008
b1010101010101101 $
b1010101010101101 3
b1010101010101101 5
1(
#1225008
0(
#1230008
0"
07
b0 #
b0 4
b0 6
b0 $
b0 3
b0 5
1,
1(
#1235008
0(
#1240008
0,
1(
#1245008
0(
#1250008
b0 %
b0 /
1"
17
1(
#1255008
0(
#1260008
1(
#1265008
0(
#1270008
b1 %
b1 /
1(
#1275008
0(
#1280008
1(
#1285008
0(
#1290008
b10 %
b10 /
1(
#1295008
0(
#1300008
1(
#1305008
0(
#1310008
b11 %
b11 /
1(
#1315008
0(
#1320008
1(
#1325008
0(
#1330008
0+
1(
#1335008
0(
#1340008
0"
07
1(
#1345008
0(
#1350008
1(
#1350009
1,
b1010 !
b1010 -
#1355009
0(
#1360009
0,
1(
#1365009
0(
#1370009
b1000100010001 )
b1000100010001 2
b0 '
b0 1
1.
1(
#1375009
0(
#1380009
b10001000100010 )
b10001000100010 2
b1 '
b1 1
1(
#1385009
0(
#1390009
b11001100110011 )
b11001100110011 2
b10 '
b10 1
1(
#1395009
0(
#1400009
b100010001000100 )
b100010001000100 2
b11 '
b11 1
1(
#1405009
0(
#1410009
b10 &
b10 0
b0 %
b0 /
1+
0.
1(
#1415009
0(
#1420009
1"
17
b11001100110011 #
b11001100110011 4
b11001100110011 6
b1000100010001 $
b1000100010001 3
b1000100010001 5
1(
#1425009
0(
#1430009
b1 &
b1 0
b1 %
b1 /
1(
#1435009
0(
#1440009
b10001000100010 #
b10001000100010 4
b10001000100010 6
b10001000100010 $
b10001000100010 3
b10001000100010 5
1(
#1445009
0(
#1450009
1(
#1450010
0"
07
b0 #
b0 4
b0 6
b0 $
b0 3
b0 5
1,
b1011 !
b1011 -
#1455010
0(
#1460010
0,
1(
#1465010
0(
#1470010
b0 )
b0 2
b0 '
b0 1
1.
0+
1"
17
1(
#1475010
0(
#1480010
b1111111111111111 )
b1111111111111111 2
b1 '
b1 1
0"
07
1(
#1485010
0(
#1490010
b1000000000000000 )
b1000000000000000 2
b10 '
b10 1
1(
#1495010
0(
#1500010
b111111111111111 )
b111111111111111 2
b11 '
b11 1
1(
#1505010
0(
#1510010
b0 %
b0 /
1+
0.
1(
#1515010
0(
#1520010
1"
17
b1111111111111111 #
b1111111111111111 4
b1111111111111111 6
1(
#1525010
0(
#1530010
b1 %
b1 /
1(
#1535010
0(
#1540010
b1111111111111111 $
b1111111111111111 3
b1111111111111111 5
1(
#1545010
0(
#1550010
b10 %
b10 /
1(
#1555010
0(
#1560010
b1000000000000000 $
b1000000000000000 3
b1000000000000000 5
1(
#1565010
0(
#1570010
b11 %
b11 /
1(
#1575010
0(
#1580010
b111111111111111 $
b111111111111111 3
b111111111111111 5
1(
#1585010
0(
#1590010
1(
#1590011
0"
07
b0 #
b0 4
b0 6
b0 $
b0 3
b0 5
1,
b1100 !
b1100 -
#1595011
0(
#1600011
0,
1(
#1605011
0(
#1610011
b1001000110100 )
b1001000110100 2
b0 '
b0 1
1.
0+
1"
17
1(
#1615011
0(
#1620011
b0 %
b0 /
b101011001111000 )
b101011001111000 2
b1 '
b1 1
1+
0"
07
1(
#1625011
0(
#1630011
0.
1(
#1635011
0(
#1640011
1"
17
b101011001111000 #
b101011001111000 4
b101011001111000 6
b1001000110100 $
b1001000110100 3
b1001000110100 5
1(
#1645011
0(
#1650011
1(
#1650012
0"
07
b0 #
b0 4
b0 6
b0 $
b0 3
b0 5
1,
b1101 !
b1101 -
#1655012
0(
#1660012
0,
1(
#1665012
0(
#1670012
b1010101111001101 )
b1010101111001101 2
b0 '
b0 1
1.
0+
1"
17
1(
#1675012
0(
#1680012
0.
0"
07
1(
#1685012
0(
#1690012
1(
#1695012
0(
#1700012
1+
1(
#1705012
0(
#1710012
1"
17
b1010101111001101 $
b1010101111001101 3
b1010101111001101 5
1(
